Elementos de Sistemas Computacionais/And16.v
/* módulo And16 */

`ifndef _And16_
`define _And16_

module And16(out, a, b);
    input [15:0] a, b;
    output [15:0] out ;

    and and0(out[0], a[0], b[0]);
    and and1(out[1], a[1], b[1]);
    and and2(out[2], a[2], b[2]);
    and and3(out[3], a[3], b[3]);
    and and4(out[4], a[4], b[4]);
    and and5(out[5], a[5], b[5]);
    and and6(out[6], a[6], b[6]);
    and and7(out[7], a[7], b[7]);
    and and8(out[8], a[8], b[8]);
    and and9(out[9], a[9], b[9]);
    and and10(out[10], a[10], b[10]);
    and and11(out[11], a[11], b[11]);
    and and12(out[12], a[12], b[12]);
    and and13(out[13], a[13], b[13]);
    and and14(out[14], a[14], b[14]);
    and and15(out[15], a[15], b[15]);

    // Descrição de conexões internas do módulo

endmodule

`endif

Elementos de Sistemas Computacionais/tb_And16.v
/* testbench para And16 */
/* ordem de portas: out, a, b */
/* input [15:0] a; input [15:0] b; */
/* output [15:0] out; */

`include "And16.v"

`define assert(signal, value) \
    if (signal !== value) \
    begin \
        $display("ASSERTION FAILED in %m: signal != value"); \
        $finish; \
    end else begin \
        $display("Success! %m: signal = value"); \
    end

module tb_And16;
    reg [15:0] a;
    reg [15:0] b;
    wire [15:0] out;

    And16 mymodule(out, a, b);
    
    initial
    begin
        $dumpfile("tb_And16.vcd");
        $dumpvars(0, tb_And16);

        a = 16'b0000001101110001; b = 16'b1100111011100000; #1;
         `assert(out, 16'b0000001001100000)
        a = 16'b0000010000101011; b = 16'b0110110100101110; #1;
         `assert(out, 16'b0000010000101010)
        a = 16'b0000101000110001; b = 16'b1010001001110001; #1;
         `assert(out, 16'b0000001000110001)
        a = 16'b0000101100110110; b = 16'b1011101001110101; #1;
         `assert(out, 16'b0000101000110100)
        a = 16'b0001010000011111; b = 16'b1111101101011001; #1;
         `assert(out, 16'b0001000000011001)
        a = 16'b0001010000100010; b = 16'b1010000110001100; #1;
         `assert(out, 16'b0000000000000000)
        a = 16'b0001101001101000; b = 16'b1010001011100110; #1;
         `assert(out, 16'b0000001001100000)
        a = 16'b0001110111010011; b = 16'b0000101010101100; #1;
         `assert(out, 16'b0000100010000000)
        a = 16'b0010011000100110; b = 16'b1001001000100101; #1;
         `assert(out, 16'b0000001000100100)
        a = 16'b0010111011101000; b = 16'b0111101001111100; #1;
         `assert(out, 16'b0010101001101000)
        a = 16'b0100010110001111; b = 16'b0100011010111110; #1;
         `assert(out, 16'b0100010010001110)
        a = 16'b0100010110100011; b = 16'b1001110100111100; #1;
         `assert(out, 16'b0000010100100000)
        a = 16'b0100110010011111; b = 16'b0111011111100000; #1;
         `assert(out, 16'b0100010010000000)
        a = 16'b0100111011000011; b = 16'b0100101100000011; #1;
         `assert(out, 16'b0100101000000011)
        a = 16'b0101111001100000; b = 16'b0100000010011001; #1;
         `assert(out, 16'b0100000000000000)
        a = 16'b0110000001111010; b = 16'b0000100001011111; #1;
         `assert(out, 16'b0000000001011010)
        a = 16'b0110000011110011; b = 16'b1100001000001111; #1;
         `assert(out, 16'b0100000000000011)
        a = 16'b0110010101001101; b = 16'b0110100001011101; #1;
         `assert(out, 16'b0110000001001101)
        a = 16'b0111000101110001; b = 16'b0111001001000110; #1;
         `assert(out, 16'b0111000001000000)
        a = 16'b0111100110011100; b = 16'b0101110010100011; #1;
         `assert(out, 16'b0101100010000000)
        a = 16'b1000010110010100; b = 16'b0000000111010001; #1;
         `assert(out, 16'b0000000110010000)
        a = 16'b1001001100101110; b = 16'b0100100000100010; #1;
         `assert(out, 16'b0000000000100010)
        a = 16'b1001101111101110; b = 16'b1000011111110001; #1;
         `assert(out, 16'b1000001111100000)
        a = 16'b1010100110010000; b = 16'b1000111011000100; #1;
         `assert(out, 16'b1000100010000000)
        a = 16'b1011110010100100; b = 16'b0100000010100111; #1;
         `assert(out, 16'b0000000010100100)
        a = 16'b1100100000010001; b = 16'b1001110100111110; #1;
         `assert(out, 16'b1000100000010000)
        a = 16'b1100100101111010; b = 16'b1011001110000001; #1;
         `assert(out, 16'b1000000100000000)
        a = 16'b1101001100011000; b = 16'b1111011010100100; #1;
         `assert(out, 16'b1101001000000000)
        a = 16'b1110101110100000; b = 16'b1111011100101101; #1;
         `assert(out, 16'b1110001100100000)
        a = 16'b1111111111111101; b = 16'b0100110100101101; #1;
         `assert(out, 16'b0100110100101101)

    end
endmodule

Elementos de Sistemas Computacionais/tb_And16.vcd
$date
	Sun Apr 23 11:46:33 2023
$end
$version
	Icarus Verilog
$end
$timescale
	1s
$end
$scope module tb_And16 $end
$var wire 16 ! out [15:0] $end
$var reg 16 " a [15:0] $end
$var reg 16 # b [15:0] $end
$scope module mymodule $end
$var wire 16 $ a [15:0] $end
$var wire 16 % b [15:0] $end
$var wire 16 & out [15:0] $end
$upscope $end
$upscope $end
$enddefinitions $end
$comment Show the parameter values. $end
$dumpall
$end
#0
$dumpvars
b1001100000 &
b1100111011100000 %
b1101110001 $
b1100111011100000 #
b1101110001 "
b1001100000 !
$end
#1
b10000101010 !
b10000101010 &
b110110100101110 #
b110110100101110 %
b10000101011 "
b10000101011 $
#2
b1000110001 !
b1000110001 &
b1010001001110001 #
b1010001001110001 %
b101000110001 "
b101000110001 $
#3
b101000110100 !
b101000110100 &
b1011101001110101 #
b1011101001110101 %
b101100110110 "
b101100110110 $
#4
b1000000011001 !
b1000000011001 &
b1111101101011001 #
b1111101101011001 %
b1010000011111 "
b1010000011111 $
#5
b0 !
b0 &
b1010000110001100 #
b1010000110001100 %
b1010000100010 "
b1010000100010 $
#6
b1001100000 !
b1001100000 &
b1010001011100110 #
b1010001011100110 %
b1101001101000 "
b1101001101000 $
#7
b100010000000 !
b100010000000 &
b101010101100 #
b101010101100 %
b1110111010011 "
b1110111010011 $
#8
b1000100100 !
b1000100100 &
b1001001000100101 #
b1001001000100101 %
b10011000100110 "
b10011000100110 $
#9
b10101001101000 !
b10101001101000 &
b111101001111100 #
b111101001111100 %
b10111011101000 "
b10111011101000 $
#10
b100010010001110 !
b100010010001110 &
b100011010111110 #
b100011010111110 %
b100010110001111 "
b100010110001111 $
#11
b10100100000 !
b10100100000 &
b1001110100111100 #
b1001110100111100 %
b100010110100011 "
b100010110100011 $
#12
b100010010000000 !
b100010010000000 &
b111011111100000 #
b111011111100000 %
b100110010011111 "
b100110010011111 $
#13
b100101000000011 !
b100101000000011 &
b100101100000011 #
b100101100000011 %
b100111011000011 "
b100111011000011 $
#14
b100000000000000 !
b100000000000000 &
b100000010011001 #
b100000010011001 %
b101111001100000 "
b101111001100000 $
#15
b1011010 !
b1011010 &
b100001011111 #
b100001011111 %
b110000001111010 "
b110000001111010 $
#16
b100000000000011 !
b100000000000011 &
b1100001000001111 #
b1100001000001111 %
b110000011110011 "
b110000011110011 $
#17
b110000001001101 !
b110000001001101 &
b110100001011101 #
b110100001011101 %
b110010101001101 "
b110010101001101 $
#18
b111000001000000 !
b111000001000000 &
b111001001000110 #
b111001001000110 %
b111000101110001 "
b111000101110001 $
#19
b101100010000000 !
b101100010000000 &
b101110010100011 #
b101110010100011 %
b111100110011100 "
b111100110011100 $
#20
b110010000 !
b110010000 &
b111010001 #
b111010001 %
b1000010110010100 "
b1000010110010100 $
#21
b100010 !
b100010 &
b100100000100010 #
b100100000100010 %
b1001001100101110 "
b1001001100101110 $
#22
b1000001111100000 !
b1000001111100000 &
b1000011111110001 #
b1000011111110001 %
b1001101111101110 "
b1001101111101110 $
#23
b1000100010000000 !
b1000100010000000 &
b1000111011000100 #
b1000111011000100 %
b1010100110010000 "
b1010100110010000 $
#24
b10100100 !
b10100100 &
b100000010100111 #
b100000010100111 %
b1011110010100100 "
b1011110010100100 $
#25
b1000100000010000 !
b1000100000010000 &
b1001110100111110 #
b1001110100111110 %
b1100100000010001 "
b1100100000010001 $
#26
b1000000100000000 !
b1000000100000000 &
b1011001110000001 #
b1011001110000001 %
b1100100101111010 "
b1100100101111010 $
#27
b1101001000000000 !
b1101001000000000 &
b1111011010100100 #
b1111011010100100 %
b1101001100011000 "
b1101001100011000 $
#28
b1110001100100000 !
b1110001100100000 &
b1111011100101101 #
b1111011100101101 %
b1110101110100000 "
b1110101110100000 $
#29
b100110100101101 !
b100110100101101 &
b100110100101101 #
b100110100101101 %
b1111111111111101 "
b1111111111111101 $
