Elementos de Sistemas Computacionais/Tarefa01_12011ECP008GabrielAlves/HalfAdder.v
/* módulo HalfAdder */

`ifndef _HalfAdder_
`define _HalfAdder_

module HalfAdder(s, c, a, b);
    input a, b;
    output s, c;

    xor xor0(s, a, b);
    and and0(c, a, b);
endmodule

`endif

Elementos de Sistemas Computacionais/FullAdder.v
/* módulo FullAdder */

`ifndef _FullAdder_
`define _FullAdder_
`include "HalfAdder.v"

module FullAdder(s, cout, a, b, cin);
    input a, b, cin;
    output cout, s;
    wire w0, w1, w2;

    HalfAdder ha0(w1, w0, a, b);
    HalfAdder ha1(s, w2, w1, cin);
    or or0(cout, w0, w2);

    // Descrição de conexões internas do módulo

endmodule

`endif

Elementos de Sistemas Computacionais/Adder16.v
/* módulo Adder16 */

`ifndef _Adder16_
`define _Adder16_

`include "HalfAdder.v"
`include "FullAdder.v"


module Adder16(s, ovfl, a, b);
    // Declarando as entradas/saidas
    input [15:0] a, b;
    output [15:0] s;
    output ovfl;
    wire [14:0] c;

    // Conexoes internas do modulo
    HalfAdder HalfAdder0(s[0], c[0], a[0], b[0]);
    FullAdder FullAdder0(s[1], c[1], a[1], b[1], c[0]);
    FullAdder FullAdder1(s[2], c[2], a[2], b[2], c[1]);
    FullAdder FullAdder2(s[3], c[3], a[3], b[3], c[2]);
    FullAdder FullAdder3(s[4], c[4], a[4], b[4], c[3]);
    FullAdder FullAdder4(s[5], c[5], a[5], b[5], c[4]);
    FullAdder FullAdder5(s[6], c[6], a[6], b[6], c[5]);
    FullAdder FullAdder6(s[7], c[7], a[7], b[7], c[6]);
    FullAdder FullAdder7(s[8], c[8], a[8], b[8], c[7]);
    FullAdder FullAdder8(s[9], c[9], a[9], b[9], c[8]);
    FullAdder FullAdder9(s[10], c[10], a[10], b[10], c[9]);
    FullAdder FullAdder10(s[11], c[11], a[11], b[11], c[10]);
    FullAdder FullAdder11(s[12], c[12], a[12], b[12], c[11]);
    FullAdder FullAdder12(s[13], c[13], a[13], b[13], c[12]);
    FullAdder FullAdder13(s[14], c[14], a[14], b[14], c[13]);
    FullAdder FullAdder14(s[15], ovfl, a[15], b[15], c[14]);

endmodule

`endif

Elementos de Sistemas Computacionais/tb_Adder16.v
/* testbench para Adder16 */
/* ordem de portas: s, ovfl, a, b */
/* input [15:0] a; input [15:0] b; */
/* output [15:0] s; output ovfl; */

`include "Adder16.v"

`define assert(signal, value) \
    if (signal !== value) \
    begin \
        $display("ASSERTION FAILED in %m: signal != value"); \
        $finish; \
    end else begin \
        $display("Success! %m: signal = value"); \
    end

module tb_Adder16;
    reg [15:0] a;
    reg [15:0] b;
    wire [15:0] s;
    wire ovfl;

    Adder16 mymodule(s, ovfl, a, b);
    
    initial
    begin
        $dumpfile("tb_Adder16.vcd");
        $dumpvars(0, tb_Adder16);

        a = 16'b0000000000000000; b = 16'b0000000000000000; #1;
         `assert(s, 16'b0000000000000000) `assert(ovfl, 1'b0)
        a = 16'b0000100001010001; b = 16'b1101111110110101; #1;
         `assert(s, 16'b1110100000000110) `assert(ovfl, 1'b0)
        a = 16'b0001000111111110; b = 16'b1001111010000011; #1;
         `assert(s, 16'b1011000010000001) `assert(ovfl, 1'b0)
        a = 16'b0001001000000101; b = 16'b1100000111011001; #1;
         `assert(s, 16'b1101001111011110) `assert(ovfl, 1'b0)
        a = 16'b0001110101100111; b = 16'b1110001110001100; #1;
         `assert(s, 16'b0000000011110011) `assert(ovfl, 1'b1)
        a = 16'b0011000010001011; b = 16'b0010101110000001; #1;
         `assert(s, 16'b0101110000001100) `assert(ovfl, 1'b0)
        a = 16'b0011111000001111; b = 16'b0110011010001111; #1;
         `assert(s, 16'b1010010010011110) `assert(ovfl, 1'b0)
        a = 16'b0100000011000000; b = 16'b0010111110100001; #1;
         `assert(s, 16'b0111000001100001) `assert(ovfl, 1'b0)
        a = 16'b0100010010110101; b = 16'b1011101010000000; #1;
         `assert(s, 16'b1111111100110101) `assert(ovfl, 1'b0)
        a = 16'b0101010010110100; b = 16'b1110101011110001; #1;
         `assert(s, 16'b0011111110100101) `assert(ovfl, 1'b1)
        a = 16'b0101111110001110; b = 16'b1101100000001011; #1;
         `assert(s, 16'b0011011110011001) `assert(ovfl, 1'b1)
        a = 16'b0111100000010101; b = 16'b1001011110000011; #1;
         `assert(s, 16'b0000111110011000) `assert(ovfl, 1'b1)
        a = 16'b0111111001010101; b = 16'b1101101100101110; #1;
         `assert(s, 16'b0101100110000011) `assert(ovfl, 1'b1)
        a = 16'b1000100010001111; b = 16'b1111100100001011; #1;
         `assert(s, 16'b1000000110011010) `assert(ovfl, 1'b1)
        a = 16'b1000100101110111; b = 16'b1101010101001010; #1;
         `assert(s, 16'b0101111011000001) `assert(ovfl, 1'b1)
        a = 16'b1001100101011001; b = 16'b1111010111100001; #1;
         `assert(s, 16'b1000111100111010) `assert(ovfl, 1'b1)
        a = 16'b1010010111111011; b = 16'b1000001000100111; #1;
         `assert(s, 16'b0010100000100010) `assert(ovfl, 1'b1)
        a = 16'b1010100101001100; b = 16'b0001101011001001; #1;
         `assert(s, 16'b1100010000010101) `assert(ovfl, 1'b0)
        a = 16'b1011101110110110; b = 16'b0111000111000011; #1;
         `assert(s, 16'b0010110101111001) `assert(ovfl, 1'b1)
        a = 16'b1011110101011101; b = 16'b1110010110111011; #1;
         `assert(s, 16'b1010001100011000) `assert(ovfl, 1'b1)
        a = 16'b1011110110011000; b = 16'b1000100100010001; #1;
         `assert(s, 16'b0100011010101001) `assert(ovfl, 1'b1)
        a = 16'b1101111011100110; b = 16'b1111100011110100; #1;
         `assert(s, 16'b1101011111011010) `assert(ovfl, 1'b1)
        a = 16'b1110001000100111; b = 16'b1011001000110010; #1;
         `assert(s, 16'b1001010001011001) `assert(ovfl, 1'b1)
        a = 16'b1110110101010011; b = 16'b0101001100001110; #1;
         `assert(s, 16'b0100000001100001) `assert(ovfl, 1'b1)
        a = 16'b1111001010001100; b = 16'b1011110110000011; #1;
         `assert(s, 16'b1011000000001111) `assert(ovfl, 1'b1)
        a = 16'b1111001100100100; b = 16'b1111111101011001; #1;
         `assert(s, 16'b1111001001111101) `assert(ovfl, 1'b1)
        a = 16'b1111010000010001; b = 16'b1101011011110111; #1;
         `assert(s, 16'b1100101100001000) `assert(ovfl, 1'b1)
        a = 16'b1111011101011011; b = 16'b1001001011101010; #1;
         `assert(s, 16'b1000101001000101) `assert(ovfl, 1'b1)
        a = 16'b1111100111001100; b = 16'b1100111001100010; #1;
         `assert(s, 16'b1100100000101110) `assert(ovfl, 1'b1)
        a = 16'b1111111111111111; b = 16'b1111111111111111; #1;
         `assert(s, 16'b1111111111111110) `assert(ovfl, 1'b1)

    end
endmodule

Elementos de Sistemas Computacionais/tb_Adder16.vcd
$date
	Tue May 02 16:40:46 2023
$end
$version
	Icarus Verilog
$end
$timescale
	1s
$end
$scope module tb_Adder16 $end
$var wire 16 ! s [15:0] $end
$var wire 1 " ovfl $end
$var reg 16 # a [15:0] $end
$var reg 16 $ b [15:0] $end
$scope module mymodule $end
$var wire 16 % a [15:0] $end
$var wire 16 & b [15:0] $end
$var wire 16 ' s [15:0] $end
$var wire 1 " ovfl $end
$var wire 15 ( c [14:0] $end
$scope module FullAdder0 $end
$var wire 1 ) a $end
$var wire 1 * b $end
$var wire 1 + cin $end
$var wire 1 , cout $end
$var wire 1 - w2 $end
$var wire 1 . w1 $end
$var wire 1 / w0 $end
$var wire 1 0 s $end
$scope module ha0 $end
$var wire 1 ) a $end
$var wire 1 * b $end
$var wire 1 / c $end
$var wire 1 . s $end
$upscope $end
$scope module ha1 $end
$var wire 1 . a $end
$var wire 1 + b $end
$var wire 1 - c $end
$var wire 1 0 s $end
$upscope $end
$upscope $end
$scope module FullAdder1 $end
$var wire 1 1 a $end
$var wire 1 2 b $end
$var wire 1 3 cin $end
$var wire 1 4 cout $end
$var wire 1 5 w2 $end
$var wire 1 6 w1 $end
$var wire 1 7 w0 $end
$var wire 1 8 s $end
$scope module ha0 $end
$var wire 1 1 a $end
$var wire 1 2 b $end
$var wire 1 7 c $end
$var wire 1 6 s $end
$upscope $end
$scope module ha1 $end
$var wire 1 6 a $end
$var wire 1 3 b $end
$var wire 1 5 c $end
$var wire 1 8 s $end
$upscope $end
$upscope $end
$scope module FullAdder10 $end
$var wire 1 9 a $end
$var wire 1 : b $end
$var wire 1 ; cin $end
$var wire 1 < cout $end
$var wire 1 = w2 $end
$var wire 1 > w1 $end
$var wire 1 ? w0 $end
$var wire 1 @ s $end
$scope module ha0 $end
$var wire 1 9 a $end
$var wire 1 : b $end
$var wire 1 ? c $end
$var wire 1 > s $end
$upscope $end
$scope module ha1 $end
$var wire 1 > a $end
$var wire 1 ; b $end
$var wire 1 = c $end
$var wire 1 @ s $end
$upscope $end
$upscope $end
$scope module FullAdder11 $end
$var wire 1 A a $end
$var wire 1 B b $end
$var wire 1 C cin $end
$var wire 1 D cout $end
$var wire 1 E w2 $end
$var wire 1 F w1 $end
$var wire 1 G w0 $end
$var wire 1 H s $end
$scope module ha0 $end
$var wire 1 A a $end
$var wire 1 B b $end
$var wire 1 G c $end
$var wire 1 F s $end
$upscope $end
$scope module ha1 $end
$var wire 1 F a $end
$var wire 1 C b $end
$var wire 1 E c $end
$var wire 1 H s $end
$upscope $end
$upscope $end
$scope module FullAdder12 $end
$var wire 1 I a $end
$var wire 1 J b $end
$var wire 1 K cin $end
$var wire 1 L cout $end
$var wire 1 M w2 $end
$var wire 1 N w1 $end
$var wire 1 O w0 $end
$var wire 1 P s $end
$scope module ha0 $end
$var wire 1 I a $end
$var wire 1 J b $end
$var wire 1 O c $end
$var wire 1 N s $end
$upscope $end
$scope module ha1 $end
$var wire 1 N a $end
$var wire 1 K b $end
$var wire 1 M c $end
$var wire 1 P s $end
$upscope $end
$upscope $end
$scope module FullAdder13 $end
$var wire 1 Q a $end
$var wire 1 R b $end
$var wire 1 S cin $end
$var wire 1 T cout $end
$var wire 1 U w2 $end
$var wire 1 V w1 $end
$var wire 1 W w0 $end
$var wire 1 X s $end
$scope module ha0 $end
$var wire 1 Q a $end
$var wire 1 R b $end
$var wire 1 W c $end
$var wire 1 V s $end
$upscope $end
$scope module ha1 $end
$var wire 1 V a $end
$var wire 1 S b $end
$var wire 1 U c $end
$var wire 1 X s $end
$upscope $end
$upscope $end
$scope module FullAdder14 $end
$var wire 1 Y a $end
$var wire 1 Z b $end
$var wire 1 [ cin $end
$var wire 1 " cout $end
$var wire 1 \ w2 $end
$var wire 1 ] w1 $end
$var wire 1 ^ w0 $end
$var wire 1 _ s $end
$scope module ha0 $end
$var wire 1 Y a $end
$var wire 1 Z b $end
$var wire 1 ^ c $end
$var wire 1 ] s $end
$upscope $end
$scope module ha1 $end
$var wire 1 ] a $end
$var wire 1 [ b $end
$var wire 1 \ c $end
$var wire 1 _ s $end
$upscope $end
$upscope $end
$scope module FullAdder2 $end
$var wire 1 ` a $end
$var wire 1 a b $end
$var wire 1 b cin $end
$var wire 1 c cout $end
$var wire 1 d w2 $end
$var wire 1 e w1 $end
$var wire 1 f w0 $end
$var wire 1 g s $end
$scope module ha0 $end
$var wire 1 ` a $end
$var wire 1 a b $end
$var wire 1 f c $end
$var wire 1 e s $end
$upscope $end
$scope module ha1 $end
$var wire 1 e a $end
$var wire 1 b b $end
$var wire 1 d c $end
$var wire 1 g s $end
$upscope $end
$upscope $end
$scope module FullAdder3 $end
$var wire 1 h a $end
$var wire 1 i b $end
$var wire 1 j cin $end
$var wire 1 k cout $end
$var wire 1 l w2 $end
$var wire 1 m w1 $end
$var wire 1 n w0 $end
$var wire 1 o s $end
$scope module ha0 $end
$var wire 1 h a $end
$var wire 1 i b $end
$var wire 1 n c $end
$var wire 1 m s $end
$upscope $end
$scope module ha1 $end
$var wire 1 m a $end
$var wire 1 j b $end
$var wire 1 l c $end
$var wire 1 o s $end
$upscope $end
$upscope $end
$scope module FullAdder4 $end
$var wire 1 p a $end
$var wire 1 q b $end
$var wire 1 r cin $end
$var wire 1 s cout $end
$var wire 1 t w2 $end
$var wire 1 u w1 $end
$var wire 1 v w0 $end
$var wire 1 w s $end
$scope module ha0 $end
$var wire 1 p a $end
$var wire 1 q b $end
$var wire 1 v c $end
$var wire 1 u s $end
$upscope $end
$scope module ha1 $end
$var wire 1 u a $end
$var wire 1 r b $end
$var wire 1 t c $end
$var wire 1 w s $end
$upscope $end
$upscope $end
$scope module FullAdder5 $end
$var wire 1 x a $end
$var wire 1 y b $end
$var wire 1 z cin $end
$var wire 1 { cout $end
$var wire 1 | w2 $end
$var wire 1 } w1 $end
$var wire 1 ~ w0 $end
$var wire 1 !" s $end
$scope module ha0 $end
$var wire 1 x a $end
$var wire 1 y b $end
$var wire 1 ~ c $end
$var wire 1 } s $end
$upscope $end
$scope module ha1 $end
$var wire 1 } a $end
$var wire 1 z b $end
$var wire 1 | c $end
$var wire 1 !" s $end
$upscope $end
$upscope $end
$scope module FullAdder6 $end
$var wire 1 "" a $end
$var wire 1 #" b $end
$var wire 1 $" cin $end
$var wire 1 %" cout $end
$var wire 1 &" w2 $end
$var wire 1 '" w1 $end
$var wire 1 (" w0 $end
$var wire 1 )" s $end
$scope module ha0 $end
$var wire 1 "" a $end
$var wire 1 #" b $end
$var wire 1 (" c $end
$var wire 1 '" s $end
$upscope $end
$scope module ha1 $end
$var wire 1 '" a $end
$var wire 1 $" b $end
$var wire 1 &" c $end
$var wire 1 )" s $end
$upscope $end
$upscope $end
$scope module FullAdder7 $end
$var wire 1 *" a $end
$var wire 1 +" b $end
$var wire 1 ," cin $end
$var wire 1 -" cout $end
$var wire 1 ." w2 $end
$var wire 1 /" w1 $end
$var wire 1 0" w0 $end
$var wire 1 1" s $end
$scope module ha0 $end
$var wire 1 *" a $end
$var wire 1 +" b $end
$var wire 1 0" c $end
$var wire 1 /" s $end
$upscope $end
$scope module ha1 $end
$var wire 1 /" a $end
$var wire 1 ," b $end
$var wire 1 ." c $end
$var wire 1 1" s $end
$upscope $end
$upscope $end
$scope module FullAdder8 $end
$var wire 1 2" a $end
$var wire 1 3" b $end
$var wire 1 4" cin $end
$var wire 1 5" cout $end
$var wire 1 6" w2 $end
$var wire 1 7" w1 $end
$var wire 1 8" w0 $end
$var wire 1 9" s $end
$scope module ha0 $end
$var wire 1 2" a $end
$var wire 1 3" b $end
$var wire 1 8" c $end
$var wire 1 7" s $end
$upscope $end
$scope module ha1 $end
$var wire 1 7" a $end
$var wire 1 4" b $end
$var wire 1 6" c $end
$var wire 1 9" s $end
$upscope $end
$upscope $end
$scope module FullAdder9 $end
$var wire 1 :" a $end
$var wire 1 ;" b $end
$var wire 1 <" cin $end
$var wire 1 =" cout $end
$var wire 1 >" w2 $end
$var wire 1 ?" w1 $end
$var wire 1 @" w0 $end
$var wire 1 A" s $end
$scope module ha0 $end
$var wire 1 :" a $end
$var wire 1 ;" b $end
$var wire 1 @" c $end
$var wire 1 ?" s $end
$upscope $end
$scope module ha1 $end
$var wire 1 ?" a $end
$var wire 1 <" b $end
$var wire 1 >" c $end
$var wire 1 A" s $end
$upscope $end
$upscope $end
$scope module HalfAdder0 $end
$var wire 1 B" a $end
$var wire 1 C" b $end
$var wire 1 D" c $end
$var wire 1 E" s $end
$upscope $end
$upscope $end
$upscope $end
$enddefinitions $end
$comment Show the parameter values. $end
$dumpall
$end
#0
$dumpvars
0E"
0D"
0C"
0B"
0A"
0@"
0?"
0>"
0="
0<"
0;"
0:"
09"
08"
07"
06"
05"
04"
03"
02"
01"
00"
0/"
0."
0-"
0,"
0+"
0*"
0)"
0("
0'"
0&"
0%"
0$"
0#"
0""
0!"
0~
0}
0|
0{
0z
0y
0x
0w
0v
0u
0t
0s
0r
0q
0p
0o
0n
0m
0l
0k
0j
0i
0h
0g
0f
0e
0d
0c
0b
0a
0`
0_
0^
0]
0\
0[
0Z
0Y
0X
0W
0V
0U
0T
0S
0R
0Q
0P
0O
0N
0M
0L
0K
0J
0I
0H
0G
0F
0E
0D
0C
0B
0A
0@
0?
0>
0=
0<
0;
0:
09
08
07
06
05
04
03
02
01
00
0/
0.
0-
0,
0+
0*
0)
b0 (
b0 '
b0 &
b0 %
b0 $
b0 #
0"
b0 !
$end
#1
1@
1;
1="
1>"
1<"
15"
16"
14"
1-"
1."
1,"
1%"
1&"
1$"
1{
1|
1P
1z
1K
1s
1D
1t
1E
10
1r
1C
18
0w
0)"
01"
09"
0A"
0H
1X
1_
1+
1k
b1110100000000110 !
b1110100000000110 '
0!"
1<
16
1u
1'"
1/"
17"
1?"
1F
1V
1]
b1111111110001 (
1D"
1n
1}
1?
1C"
12
1i
1q
1#"
1+"
13"
1;"
1:
1B
1R
1Z
1B"
1h
1x
19
b1101111110110101 $
b1101111110110101 &
b100001010001 #
b100001010001 %
#2
1l
1$"
1j
1{
1c
0!"
1|
1d
1z
1b
1s
14
0w
1t
08
15
1r
00
13
1C
0o
1k
0X
0+
1,
0g
1)"
0&"
0@
1=
1<
1H
0E
1m
0n
0V
b1011000010000001 !
b1011000010000001 '
1E"
b1111111111110 (
0D"
1/
1e
0'"
1("
1>
0?
0F
1G
1*
02
0i
0q
0+"
0R
0B"
1)
11
1`
1p
1""
1*"
09
1A
b1001111010000011 $
b1001111010000011 &
b1000111111110 #
b1000111111110 %
#3
0r
0k
1o
0l
0j
0<"
0c
05"
1g
0d
0$"
19"
06"
0b
0{
04"
04
1!"
0|
0-"
0;
0C
0P
18
05
0z
11"
0."
0="
0<
0K
10
03
0s
0,"
0A"
0>"
0@
0=
1H
0E
0D
1X
1+
0,
0w
0t
1)"
0&"
0%"
0?"
0>
1F
0G
1V
b1101001111011110 !
b1101001111011110 '
0E"
b1 (
1D"
0/
0u
1'"
0("
0*
1a
1i
1y
1+"
03"
0;"
0:
0B
1R
1B"
0)
0`
0h
0p
0x
0""
0*"
12"
b1100000111011001 $
b1100000111011001 &
b1001000000101 #
b1001000000101 %
#4
1"
0_
1\
1[
1T
0X
1U
1S
1L
1M
1K
1D
0H
1E
1C
1<
1=
1;
1="
1>"
1j
1<"
1c
15"
0g
1d
03
09"
16"
1b
0,
14"
0+
08
14
1o
0P
10
0-
1w
01"
1-"
0A"
0@
b11110011 !
b11110011 '
1E"
b111111100001100 (
0D"
06
17
0m
1N
1.
1u
0/"
10"
1?"
1>
0C"
12
0i
0y
13"
1J
1)
1p
1x
1*"
02"
1:"
19
b1110001110001100 $
b1110001110001100 &
b1110101100111 #
b1110101100111 %
#5
0K
0D
1H
0E
0o
0C
18
0j
1<"
0<
13
0c
15"
1@
0=
1,
0[
1g
0d
1."
09"
16"
0;
00
1-
0T
0"
0b
1,"
14"
0="
1+
1X
0U
0_
0\
04
0w
0!"
0)"
1%"
01"
1-"
1A"
0>"
0P
0M
b101110000001100 !
b101110000001100 '
0E"
b10001110000011 (
1D"
0V
0]
07
0u
0}
0'"
1("
1/"
00"
0?"
0N
1O
1C"
02
0a
1:
0R
0Z
01
1`
0p
0x
1""
0*"
0:"
09
1I
b10101110000001 $
b10101110000001 &
b11000010001011 #
b11000010001011 %
#6
1P
1K
1D
0H
1E
1C
1_
1<
1o
04"
1[
0@
1=
1j
0-"
1T
1b
0,"
1;
10
0-
1g
1c
01"
0."
0X
1U
14
1)"
0%"
b1010010010011110 !
b1010010010011110 '
09"
06"
b111111000001111 (
1="
0.
1/
0e
1f
0/"
1V
17
1'"
0("
07"
18"
1@"
1*
12
1a
0+"
1;"
0:
1R
11
0""
12"
1:"
19
b110011010001111 $
b110011010001111 &
b11111000001111 #
b11111000001111 %
#7
16"
0_
14"
1C
0[
1-"
1<
0T
08
0g
0o
1."
0@
1=
0K
1X
0U
00
03
0b
0j
1,"
1<"
1;
0D
0S
1w
01"
0+
0,
04
0c
1!"
0)"
1%"
09"
15"
0A"
1>"
1="
1H
0E
1P
0M
0L
1u
1/"
b111000001100001 !
b111000001100001 '
1E"
b111110000000 (
0D"
0/
07
0f
1}
0'"
1("
17"
08"
1?"
0@"
0F
1N
0O
0*
02
0a
1q
1+"
1:
0R
0B"
0)
01
0`
1x
1""
02"
0:"
09
0A
0I
1Q
b10111110100001 $
b10111110100001 &
b100000011000000 #
b100000011000000 %
#8
0C
0<
0"
1@
0=
0\
0;
0[
0="
0T
1A"
0>"
1X
0U
0<"
0S
05"
0L
19"
06"
1P
0M
04"
0K
0-"
b10000000 (
0D
11"
0."
1H
0E
1_
18
1o
b1111111100110101 !
b1111111100110101 '
0!"
0/"
1F
1]
16
1m
0}
0C"
0q
0+"
0;"
1B
1Z
1B"
11
1h
1p
0x
1:"
b1011101010000000 $
b1011101010000000 &
b100010010110101 #
b100010010110101 %
#9
1)"
1$"
1{
1"
1|
0_
1\
1r
1z
1[
0o
1k
1w
1s
0!"
b11111110100101 !
b11111110100101 '
0X
b100000011110000 (
1T
0m
1n
0u
1v
1}
0V
1W
1C"
1i
1q
1y
0B
1R
0B"
1A
b1110101011110001 $
b1110101011110001 &
b101010010110100 #
b101010010110100 %
#10
0;
0="
1A"
0>"
1g
0<"
1b
05"
14
19"
06"
0$"
08
15
1o
0w
04"
0{
0,"
1K
13
1j
0r
0z
0-"
1C
0!"
0|
1)"
0&"
0%"
1H
1D
1P
1,
1c
0k
0s
11"
0."
b11011110011001 !
b11011110011001 '
0@
b101100000001110 (
1<
0}
1'"
0("
0F
1G
0N
1/
1f
0n
0v
1/"
0>
1?
1*
1a
0i
0q
0y
0#"
03"
1B
0J
1)
1`
0h
0p
1*"
12"
19
b1101100000001011 $
b1101100000001011 &
b101111110001110 #
b101111110001110 %
#11
1g
1b
1"
14
0w
1U
0H
0_
1\
08
15
0r
1S
0C
1[
1-
13
0j
0k
1L
1@
0<
0X
1T
1+
00
1,
0c
1o
0l
0P
1M
1>
0?
1V
0W
b111110011000 !
b111110011000 '
0E"
b111000000000111 (
1D"
1.
0/
0f
1m
1N
0a
1#"
1+"
13"
1;"
0:
0R
1B"
0)
0`
1h
0""
0*"
02"
0:"
1I
b1001011110000011 $
b1001011110000011 &
b111100000010101 #
b111100000010101 %
#12
1$"
1{
1|
1z
1s
1t
1r
1k
1;
03
0o
1l
1="
0,
1j
1H
0A"
1>"
10
0-
1c
1C
1<"
0+
08
05
0g
1d
0w
1)"
1@
1<
1X
0U
0!"
09"
15"
b101100110000011 !
b101100110000011 '
1E"
b111111001111100 (
0D"
06
17
1e
1u
0'"
0>
1?
0V
1W
1}
07"
18"
0C"
12
1a
1q
0#"
0;"
1:
1R
1x
12"
1:"
b1101101100101110 $
b1101101100101110 &
b111111001010101 #
b111111001010101 %
#13
09"
04"
0-"
1S
11"
0."
0@
1L
0z
15
0r
0$"
0,"
0;
0P
1M
1b
0s
13
0k
0{
0%"
0<"
0="
1K
1[
1+
08
14
0w
0t
10
1,
1g
0d
1o
0l
0!"
0|
1)"
0&"
05"
0A"
0>"
0H
1E
1D
0X
1U
1T
1_
0\
b1000000110011010 !
b1000000110011010 '
0E"
b111100000001111 (
1D"
16
07
0u
0.
1/
0e
1f
0m
0}
1'"
08"
0?"
1F
0G
1V
0W
0]
1^
1C"
02
0q
03"
1J
1)
1`
0h
0x
1""
02"
0:"
0A
0I
0Q
1Y
b1111100100001011 $
b1111100100001011 &
b1000100010001111 #
b1000100010001111 %
#14
0_
1!"
0[
1z
0K
0T
1s
0D
1X
0U
1t
1H
0E
0S
1r
19"
00
0C
0L
1j
1k
1$"
14"
0+
1A"
1@
0<
0P
0M
0g
1d
1c
0o
1l
0w
1{
1)"
01"
1-"
b101111011000001 !
b101111011000001 '
1E"
b101111110 (
0D"
1?"
1>
0?
0N
1e
0f
1m
1u
1~
0'"
0/"
10"
0C"
1y
1;"
0:
0J
0`
1h
1p
1x
0""
1*"
b1101010101001010 $
b1101010101001010 &
b1000100101110111 #
b1000100101110111 %
#15
0!"
0z
0s
1w
0t
0r
1_
0k
1[
1o
0l
1T
0j
0X
1U
0c
1S
11"
1g
0d
1L
1,"
0b
1M
10
1%"
03
04
1K
1+
0)"
1&"
0P
0,
08
05
0H
1D
b1000111100111010 !
b1000111100111010 '
0E"
b111000111000001 (
1D"
1'"
1N
0/
06
0F
1G
1C"
0*
0a
1q
1#"
1J
0)
01
1`
0p
1A
b1111010111100001 $
b1111010111100001 &
b1001100101011001 #
b1001100101011001 %
#16
1r
1k
0o
1l
1j
1c
1;
0g
1d
1,"
1="
1b
0S
1%"
0A"
1>"
0_
14
0L
0)"
1&"
1<"
0[
15
1|
1P
0M
1$"
14"
15"
0T
13
1z
0K
08
0!"
1{
01"
1."
1-"
09"
16"
0X
0U
1,
1w
1s
b10100000100010 !
b10100000100010 '
1@
b11111111111 (
0D
16
1}
0~
1/"
00"
17"
0V
1/
0u
1v
0>
0G
1*
12
0y
0#"
0+"
13"
0;"
0B
0J
0R
1)
1p
1""
1:"
09
0A
1I
b1000001000100111 $
b1000001000100111 &
b1010010111111011 #
b1010010111111011 %
#17
1X
1S
1L
0P
1M
0b
1K
04
0w
0@
1D
18
05
0r
0;
1E
00
03
0k
0z
0="
1C
0g
0d
0!"
0|
0H
1_
0"
0+
0,
1o
0l
0s
1A"
0>"
1<
0e
1f
0}
1~
1F
1]
0^
b1100010000010101 !
b1100010000010101 '
1E"
b11101111001000 (
0D"
0/
0m
0v
0?"
1?
0*
02
1a
0q
1y
1#"
1:
1B
0Z
0B"
0)
11
0h
0p
0""
0:"
19
b1101011001001 $
b1101011001001 &
b1010100101001100 #
b1010100101001100 %
#18
0|
1g
0z
1"
1b
0s
0_
1\
14
0t
1[
08
15
0r
0C
1T
13
0j
0k
0$"
11"
0."
1@
0<
1P
0M
0X
1U
1,
0c
1o
0l
1w
1!"
b111001110000110 (
0{
0)"
0&"
b10110101111001 !
b10110101111001 '
0H
0E
0/"
10"
1>
0?
0N
1O
1V
1/
0f
1m
1u
1}
0~
0'"
1("
0F
1G
1*
0a
1+"
03"
0:
1J
1R
1)
0`
1h
1p
0x
1""
12"
1A
b111000111000011 $
b111000111000011 &
b1011101110110110 #
b1011101110110110 %
#19
1&"
1$"
1{
0!"
1|
1g
1E
1z
1b
1C
1s
14
0A"
1<
0w
1t
1P
08
15
11"
0<"
0@
1=
1r
1K
1-
13
1j
1,"
05"
1;
1o
1k
0H
1D
1_
0\
1+
00
1,
1c
0)"
1%"
19"
06"
1="
0m
1n
1F
0G
0]
1^
b1010001100011000 !
b1010001100011000 '
0E"
b111110111111111 (
1D"
1.
0/
1f
1'"
0("
07"
1@"
1a
1i
1q
0y
1;"
0B
1Z
1B"
0)
1`
0p
1x
0""
02"
1:"
b1110010110111011 $
b1110010110111011 &
b1011110101011101 #
b1011110101011101 %
#20
01"
0,"
0%"
0_
1)"
0&"
03
0o
0z
0[
0b
0$"
0,
0j
0s
0;
1S
0T
04
0{
0-
1g
0d
0c
1w
0t
1A"
0="
0@
0=
0P
1M
1L
1X
0U
0+
08
05
0!"
0|
0.
1e
0f
0u
1?"
0@"
0>
1?
1N
0O
0V
b100011010101001 !
b100011010101001 '
1E"
b11100100010000 (
0D"
06
0}
0*
0a
0q
0#"
0;"
1:
0J
0R
0B"
01
0x
1""
b1000100100010001 $
b1000100100010001 &
b1011110110011000 #
b1011110110011000 %
#21
0@
0;
0="
1A"
0>"
11"
0w
1!"
0<"
1_
1,"
1b
0r
1z
1$"
04"
05"
1[
1)"
1%"
1H
0E
10
14
1g
1o
0k
1s
1{
0-"
19"
06"
b111100011100100 (
1T
b1101011111011010 !
b1101011111011010 '
0E"
0'"
1("
0F
1G
1.
17
0e
1m
0n
1v
1~
00"
17"
1W
0C"
12
1q
1y
1#"
0+"
1B
1J
1R
1)
11
0`
0h
1p
1x
0*"
12"
0I
1Q
b1111100011110100 $
b1111100011110100 &
b1101111011100110 #
b1101111011100110 %
#22
15
1g
1_
0)"
01"
13
1b
1<"
1[
0$"
0,"
0C
0K
00
1,
08
14
09"
15"
0X
1U
1T
0{
0%"
1A"
0<
1H
0E
b110001000100110 (
0D
0P
0M
0.
1/
16
07
07"
18"
1V
0W
b1001010001011001 !
b1001010001011001 '
1E"
0~
0("
0?"
0?
1F
0G
0N
1O
1*
02
0y
0#"
13"
0:
0R
1B"
0x
0""
0:"
09
0A
1I
b1011001000110010 $
b1011001000110010 &
b1110001000100111 #
b1110001000100111 %
#23
1M
1K
1D
1w
0H
1E
1r
1C
1k
1<
0o
1l
0)"
1=
1j
0$"
16"
1;
1c
1S
0z
0{
14"
1<"
1="
0g
1d
0P
1L
1X
0U
0_
1\
1"
0s
1!"
0|
1-"
09"
b111111100011110 (
15"
0A"
1>"
b100000001100001 !
b100000001100001 '
0@
1e
1N
0O
0V
1W
1]
0^
0v
1}
10"
17"
08"
1?"
1>
12
1a
0i
0q
1+"
0J
1R
0Z
01
1h
0p
1x
1*"
02"
1:"
19
b101001100001110 $
b101001100001110 &
b1110110101010011 #
b1110110101010011 %
#24
1C
1<
0@
1=
0j
1;
0c
1="
1g
0d
0A"
1>"
0b
1<"
04
0w
15"
18
05
0r
1."
09"
16"
1[
03
0k
1,"
14"
1P
0M
0X
1U
1T
1_
0\
10
0,
0o
0l
0!"
1%"
01"
b111111110000000 (
1-"
b1011000000001111 !
b1011000000001111 '
1H
0E
0N
1O
1V
0W
0]
1^
1.
0/
0m
0}
1("
1/"
00"
0F
1G
1C"
02
0a
1#"
03"
1;"
1:
1J
0R
1Z
0B"
0)
11
1`
0h
0x
1""
0*"
12"
0:"
09
1A
b1011110110000011 $
b1011110110000011 &
b1111001010001100 #
b1111001010001100 %
