Elementos de Sistemas Computacionais/DLatch.v
/* módulo DLatch */

`ifndef _DLatch_
`define _DLatch_

module DLatch(q, d, clk);
    input d, clk;
    output q;
    wire w1, w2, w3, w4, w5, w6, w7, w8, w9, nq;

    nand nand1(w2, d, clk);
    not not1(w1, d);
    nand nand2(w5, w2, w3);
    nand nand3(w4, clk, w1);
    nand nand4(w3, w5, w4);
    not not2(w7, clk);
    not not3(w6, w5);
    nand nand5(w8, w5, w7);
    nand nand6(q, w8, nq);
    nand nand7(w9, w7, w6);
    nand nand8(nq, q, w9);

    // Descrição de conexões internas do módulo

endmodule

`endif

Elementos de Sistemas Computacionais/Mux.v
/* módulo Mux */

`ifndef _Mux_
`define _Mux_

module Mux(out, a, b, sel);
    input a, b, sel;
    output out;
    wire w0, w1, w2;

    
    nand nand0(w0, a, w2);
    nand nand1(w1, b, sel);
    nand nand2(out, w0, w1);
    not not0(w2, sel);

    // Descrição de conexões internas do módulo

endmodule

`endif

Elementos de Sistemas Computacionais/Bit.v
/* módulo Bit */

`ifndef _Bit_
`define _Bit_

`include "Mux.v"
`include "DLatch.v"

module Bit(out, in, load, clk);
    input in, load, clk;
    output out;
    wire w0, w1;

    Mux mux0(w0, w1, in, load);
    DLatch dff(w1, w0, clk);

    assign out = w1;


    // Descrição de conexões internas do módulo

endmodule

`endif

Elementos de Sistemas Computacionais/tb_Bit.v
/* testbench para Bit */
/* ordem de portas: out, in, load, clk */
/* input in, load, clk; */
/* output out; */

`include "Bit.v"

`define assert(signal, value) \
    if (signal !== value) \
    begin \
        $display("ASSERTION FAILED in %m: signal != value"); \
        $finish; \
    end else begin \
        $display("Success! %m: signal = value"); \
    end

module tb_Bit;
    reg in, load, clk;
    wire out;

    Bit bit0(out, in, load, clk);
    
    always
    begin
        #1 clk = ~clk;
    end
    
    initial
    begin
        $dumpfile("tb_Bit.vcd");
        $dumpvars(0, tb_Bit);

        clk = 0;

        in = 0; load = 1; #3;
        `assert(out, 1'b0)

        in = 0; load = 0; #3;
        `assert(out, 1'b0)
    
        in = 0; load = 1; #3;
        `assert(out, 1'b0)

        in = 1; load = 0; #3;
        `assert(out, 1'b0)

        in = 1; load = 1; #3;
        `assert(out, 1'b1)

        in = 0; load = 0; #3;
        `assert(out, 1'b1)

        $finish;
    end

endmodule

Elementos de Sistemas Computacionais/tb_Bit.vcd
$date
	Sun Apr 23 11:34:59 2023
$end
$version
	Icarus Verilog
$end
$timescale
	1s
$end
$scope module tb_Bit $end
$var wire 1 ! out $end
$var reg 1 " clk $end
$var reg 1 # in $end
$var reg 1 $ load $end
$scope module bit0 $end
$var wire 1 " clk $end
$var wire 1 # in $end
$var wire 1 $ load $end
$var wire 1 ! out $end
$var wire 1 % w1 $end
$var wire 1 & w0 $end
$scope module dff $end
$var wire 1 " clk $end
$var wire 1 ' nq $end
$var wire 1 % q $end
$var wire 1 ( w1 $end
$var wire 1 ) w2 $end
$var wire 1 * w3 $end
$var wire 1 + w4 $end
$var wire 1 , w5 $end
$var wire 1 - w6 $end
$var wire 1 . w7 $end
$var wire 1 / w8 $end
$var wire 1 0 w9 $end
$var wire 1 & d $end
$upscope $end
$scope module mux0 $end
$var wire 1 % a $end
$var wire 1 # b $end
$var wire 1 & out $end
$var wire 1 $ sel $end
$var wire 1 1 w0 $end
$var wire 1 2 w1 $end
$var wire 1 3 w2 $end
$upscope $end
$upscope $end
$upscope $end
$enddefinitions $end
$comment Show the parameter values. $end
$dumpall
$end
#0
$dumpvars
03
12
11
x0
x/
1.
x-
x,
1+
x*
1)
1(
x'
0&
x%
1$
0#
0"
x!
$end
#1
1-
0,
1*
1/
10
0+
0.
1"
#2
0!
0%
1'
00
1+
1.
0"
#3
10
0+
0.
13
1"
0$
#4
00
1+
1.
0"
#5
10
0+
0.
1"
#6
00
1+
1.
03
0"
1$
#7
10
0+
0.
1"
#8
00
1+
1.
0"
#9
10
0+
0.
13
1"
0$
1#
#10
00
1+
1.
0"
#11
10
0+
0.
1"
#12
0(
00
1&
1+
1.
02
03
0"
1$
#13
0*
0-
1,
10
0)
0.
1"
#14
0'
1!
1%
0/
1)
1.
0"
#15
0*
1+
0(
1/
01
1&
0)
0.
13
12
1"
0$
0#
#16
0/
1)
1.
0"
#17
1/
0)
0.
1"
#18
0/
1)
1.
0"
