Elementos de Sistemas Computacionais/DMux.v
/* módulo DMux */

`ifndef _DMux_
`define _DMux_

module DMux(a, b, in, sel);
    input in, sel;
    output a, b;
    wire w0;

    and and0(b, in, sel);
    not not0(w0, sel);
    and and1(a, in, w0);
    // Descrição de conexões internas do módulo

endmodule

`endif

Elementos de Sistemas Computacionais/DMux4Way.v
/* módulo DMux4Way */

`ifndef _DMux4Way_
`define _DMux4Way_

`include "DMux.v"

module DMux4Way(a, b, c, d, in, sel);
    input in;
    input [1:0] sel;
    output a, b, c, d;
    wire w0, w1;

    // 

    DMux dmux0(w0, w1, in, sel[1]);
    DMux dmux1(a, b, w0, sel[0]);
    DMux dmux2(c, d, w1, sel[0]);

endmodule

`endif

Elementos de Sistemas Computacionais/tb_DMux4Way.v
/* testbench para DMux4Way */
/* ordem de portas: a, b, c, d, in, sel */
/* input in; input [1:0] sel; */
/* output a; output b; output c; output d; */

`include "DMux4Way.v"

`define assert(signal, value) \
    if (signal !== value) \
    begin \
        $display("ASSERTION FAILED in %m: signal != value"); \
        $finish; \
    end else begin \
        $display("Success! %m: signal = value"); \
    end

module tb_DMux4Way;
    reg in;
    reg [1:0] sel;
    wire a;
    wire b;
    wire c;
    wire d;

    DMux4Way mymodule(a, b, c, d, in, sel);
    
    initial
    begin
        $dumpfile("tb_DMux4Way.vcd");
        $dumpvars(0, tb_DMux4Way);

        in = 1'b0; sel = 2'b00; #1;
         `assert(a, 1'b0) `assert(b, 1'b0) `assert(c, 1'b0) `assert(d, 1'b0)
        in = 1'b0; sel = 2'b01; #1;
         `assert(a, 1'b0) `assert(b, 1'b0) `assert(c, 1'b0) `assert(d, 1'b0)
        in = 1'b0; sel = 2'b10; #1;
         `assert(a, 1'b0) `assert(b, 1'b0) `assert(c, 1'b0) `assert(d, 1'b0)
        in = 1'b0; sel = 2'b11; #1;
         `assert(a, 1'b0) `assert(b, 1'b0) `assert(c, 1'b0) `assert(d, 1'b0)
        in = 1'b1; sel = 2'b00; #1;
         `assert(a, 1'b1) `assert(b, 1'b0) `assert(c, 1'b0) `assert(d, 1'b0)
        in = 1'b1; sel = 2'b01; #1;
         `assert(a, 1'b0) `assert(b, 1'b1) `assert(c, 1'b0) `assert(d, 1'b0)
        in = 1'b1; sel = 2'b10; #1;
         `assert(a, 1'b0) `assert(b, 1'b0) `assert(c, 1'b1) `assert(d, 1'b0)
        in = 1'b1; sel = 2'b11; #1;
         `assert(a, 1'b0) `assert(b, 1'b0) `assert(c, 1'b0) `assert(d, 1'b1)

    end
endmodule

Elementos de Sistemas Computacionais/tb_DMux4Way.vcd
$date
	Sun Apr 23 11:24:42 2023
$end
$version
	Icarus Verilog
$end
$timescale
	1s
$end
$scope module tb_DMux4Way $end
$var wire 1 ! d $end
$var wire 1 " c $end
$var wire 1 # b $end
$var wire 1 $ a $end
$var reg 1 % in $end
$var reg 2 & sel [1:0] $end
$scope module mymodule $end
$var wire 1 % in $end
$var wire 2 ' sel [1:0] $end
$var wire 1 ( w1 $end
$var wire 1 ) w0 $end
$var wire 1 ! d $end
$var wire 1 " c $end
$var wire 1 # b $end
$var wire 1 $ a $end
$scope module dmux0 $end
$var wire 1 ) a $end
$var wire 1 ( b $end
$var wire 1 % in $end
$var wire 1 * sel $end
$var wire 1 + w0 $end
$upscope $end
$scope module dmux1 $end
$var wire 1 $ a $end
$var wire 1 # b $end
$var wire 1 ) in $end
$var wire 1 , sel $end
$var wire 1 - w0 $end
$upscope $end
$scope module dmux2 $end
$var wire 1 " a $end
$var wire 1 ! b $end
$var wire 1 ( in $end
$var wire 1 . sel $end
$var wire 1 / w0 $end
$upscope $end
$upscope $end
$upscope $end
$enddefinitions $end
$comment Show the parameter values. $end
$dumpall
$end
#0
$dumpvars
1/
0.
1-
0,
1+
0*
0)
0(
b0 '
b0 &
0%
0$
0#
0"
0!
$end
#1
0-
0/
1,
1.
b1 &
b1 '
#2
0+
1-
1/
1*
0,
0.
b10 &
b10 '
#3
0-
0/
1,
1.
b11 &
b11 '
#4
1$
1)
1+
1-
1/
0*
0,
0.
0(
b0 &
b0 '
1%
#5
0$
1#
0-
0/
1,
1.
b1 &
b1 '
#6
0)
0$
1"
1(
0+
0#
1-
1/
1*
0,
0.
b10 &
b10 '
#7
0"
0-
1!
0/
1,
1.
b11 &
b11 '
