Elementos de Sistemas Computacionais/DMux.v
/* módulo DMux */

`ifndef _DMux_
`define _DMux_

module DMux(a, b, in, sel);
    input in, sel;
    output a, b;
    wire w0;

    and and0(b, in, sel);
    not not0(w0, sel);
    and and1(a, in, w0);
    // Descrição de conexões internas do módulo

endmodule

`endif

Elementos de Sistemas Computacionais/DMux16.v
/* módulo DMux16 */

`ifndef _DMux16_
`define _DMux16_

`include "DMux.v"

module DMux16(a, b, in, sel);
    input [15:0] in; 
    input sel;
    output [15:0] a, b;

    DMux dmux16_0(a[0], b[0], in[0], sel);
    DMux dmux16_1(a[1], b[1], in[1], sel);
    DMux dmux16_2(a[2], b[2], in[2], sel);
    DMux dmux16_3(a[3], b[3], in[3], sel);
    DMux dmux16_4(a[4], b[4], in[4], sel);
    DMux dmux16_5(a[5], b[5], in[5], sel);
    DMux dmux16_6(a[6], b[6], in[6], sel);
    DMux dmux16_7(a[7], b[7], in[7], sel);
    DMux dmux16_8(a[8], b[8], in[8], sel);
    DMux dmux16_9(a[9], b[9], in[9], sel);
    DMux dmux16_10(a[10], b[10], in[10], sel);
    DMux dmux16_11(a[11], b[11], in[11], sel);
    DMux dmux16_12(a[12], b[12], in[12], sel);
    DMux dmux16_13(a[13], b[13], in[13], sel);
    DMux dmux16_14(a[14], b[14], in[14], sel);
    DMux dmux16_15(a[15], b[15], in[15], sel);



endmodule

`endif

Elementos de Sistemas Computacionais/DMux4Way16.v
/* módulo DMux4Way16 */

`ifndef _DMux4Way16_
`define _DMux4Way16_

`include "DMux16.v"

module DMux4Way16(a, b, c, d, in, sel);
    input [15:0] in;
    input [1:0] sel;
    output [15:0] a, b, c, d ;
    wire [15:0] w0, w1;

    // 

    DMux16 dmux16_0(w0, w1, in, sel[1]);
    DMux16 dmux16_1(a, b, w0, sel[0]);
    DMux16 dmux16_2(c, d, w1, sel[0]);

endmodule

`endif

Elementos de Sistemas Computacionais/tb_DMux4Way16.v
/* testbench para DMux4Way16 */
/* ordem de portas: a, b, c, d, in, sel */
/* input [15:0] in; input [1:0] sel; */
/* output [15:0] a; output [15:0] b; output [15:0] c; output [15:0] d; */

`include "DMux4Way16.v"

`define assert(signal, value) \
    if (signal !== value) \
    begin \
        $display("ASSERTION FAILED in %m: signal != value"); \
        $finish; \
    end else begin \
        $display("Success! %m: signal = value"); \
    end

module tb_DMux4Way16;
    reg [15:0] in;
    reg [1:0] sel;
    wire [15:0] a;
    wire [15:0] b;
    wire [15:0] c;
    wire [15:0] d;

    DMux4Way16 mymodule(a, b, c, d, in, sel);
    
    initial
    begin
        $dumpfile("tb_DMux4Way16.vcd");
        $dumpvars(0, tb_DMux4Way16);

        in = 16'b0000000000000000; sel = 2'b00; #1;
         `assert(a, 16'b0000000000000000) `assert(b, 16'b0000000000000000) `assert(c, 16'b0000000000000000) `assert(d, 16'b0000000000000000)
        in = 16'b0000001100111010; sel = 2'b01; #1;
         `assert(a, 16'b0000000000000000) `assert(b, 16'b0000001100111010) `assert(c, 16'b0000000000000000) `assert(d, 16'b0000000000000000)
        in = 16'b0000010000100110; sel = 2'b10; #1;
         `assert(a, 16'b0000000000000000) `assert(b, 16'b0000000000000000) `assert(c, 16'b0000010000100110) `assert(d, 16'b0000000000000000)
        in = 16'b0001110110010111; sel = 2'b01; #1;
         `assert(a, 16'b0000000000000000) `assert(b, 16'b0001110110010111) `assert(c, 16'b0000000000000000) `assert(d, 16'b0000000000000000)
        in = 16'b0010001101011001; sel = 2'b01; #1;
         `assert(a, 16'b0000000000000000) `assert(b, 16'b0010001101011001) `assert(c, 16'b0000000000000000) `assert(d, 16'b0000000000000000)
        in = 16'b0010011111100000; sel = 2'b00; #1;
         `assert(a, 16'b0010011111100000) `assert(b, 16'b0000000000000000) `assert(c, 16'b0000000000000000) `assert(d, 16'b0000000000000000)
        in = 16'b0010111000000001; sel = 2'b10; #1;
         `assert(a, 16'b0000000000000000) `assert(b, 16'b0000000000000000) `assert(c, 16'b0010111000000001) `assert(d, 16'b0000000000000000)
        in = 16'b0011100101100101; sel = 2'b10; #1;
         `assert(a, 16'b0000000000000000) `assert(b, 16'b0000000000000000) `assert(c, 16'b0011100101100101) `assert(d, 16'b0000000000000000)
        in = 16'b0011110011001111; sel = 2'b11; #1;
         `assert(a, 16'b0000000000000000) `assert(b, 16'b0000000000000000) `assert(c, 16'b0000000000000000) `assert(d, 16'b0011110011001111)
        in = 16'b0100100110100000; sel = 2'b00; #1;
         `assert(a, 16'b0100100110100000) `assert(b, 16'b0000000000000000) `assert(c, 16'b0000000000000000) `assert(d, 16'b0000000000000000)
        in = 16'b0100111010101010; sel = 2'b01; #1;
         `assert(a, 16'b0000000000000000) `assert(b, 16'b0100111010101010) `assert(c, 16'b0000000000000000) `assert(d, 16'b0000000000000000)
        in = 16'b0101100000100110; sel = 2'b00; #1;
         `assert(a, 16'b0101100000100110) `assert(b, 16'b0000000000000000) `assert(c, 16'b0000000000000000) `assert(d, 16'b0000000000000000)
        in = 16'b0101111110101101; sel = 2'b11; #1;
         `assert(a, 16'b0000000000000000) `assert(b, 16'b0000000000000000) `assert(c, 16'b0000000000000000) `assert(d, 16'b0101111110101101)
        in = 16'b0110101110110101; sel = 2'b01; #1;
         `assert(a, 16'b0000000000000000) `assert(b, 16'b0110101110110101) `assert(c, 16'b0000000000000000) `assert(d, 16'b0000000000000000)
        in = 16'b0110111010011011; sel = 2'b10; #1;
         `assert(a, 16'b0000000000000000) `assert(b, 16'b0000000000000000) `assert(c, 16'b0110111010011011) `assert(d, 16'b0000000000000000)
        in = 16'b0111111100110111; sel = 2'b11; #1;
         `assert(a, 16'b0000000000000000) `assert(b, 16'b0000000000000000) `assert(c, 16'b0000000000000000) `assert(d, 16'b0111111100110111)
        in = 16'b1000000110001110; sel = 2'b11; #1;
         `assert(a, 16'b0000000000000000) `assert(b, 16'b0000000000000000) `assert(c, 16'b0000000000000000) `assert(d, 16'b1000000110001110)
        in = 16'b1000001110110011; sel = 2'b10; #1;
         `assert(a, 16'b0000000000000000) `assert(b, 16'b0000000000000000) `assert(c, 16'b1000001110110011) `assert(d, 16'b0000000000000000)
        in = 16'b1001010100111000; sel = 2'b11; #1;
         `assert(a, 16'b0000000000000000) `assert(b, 16'b0000000000000000) `assert(c, 16'b0000000000000000) `assert(d, 16'b1001010100111000)
        in = 16'b1010011010110100; sel = 2'b00; #1;
         `assert(a, 16'b1010011010110100) `assert(b, 16'b0000000000000000) `assert(c, 16'b0000000000000000) `assert(d, 16'b0000000000000000)
        in = 16'b1010111111001101; sel = 2'b00; #1;
         `assert(a, 16'b1010111111001101) `assert(b, 16'b0000000000000000) `assert(c, 16'b0000000000000000) `assert(d, 16'b0000000000000000)
        in = 16'b1011101000110011; sel = 2'b11; #1;
         `assert(a, 16'b0000000000000000) `assert(b, 16'b0000000000000000) `assert(c, 16'b0000000000000000) `assert(d, 16'b1011101000110011)
        in = 16'b1100000000101001; sel = 2'b01; #1;
         `assert(a, 16'b0000000000000000) `assert(b, 16'b1100000000101001) `assert(c, 16'b0000000000000000) `assert(d, 16'b0000000000000000)
        in = 16'b1101001111110111; sel = 2'b00; #1;
         `assert(a, 16'b1101001111110111) `assert(b, 16'b0000000000000000) `assert(c, 16'b0000000000000000) `assert(d, 16'b0000000000000000)
        in = 16'b1101010000110001; sel = 2'b01; #1;
         `assert(a, 16'b0000000000000000) `assert(b, 16'b1101010000110001) `assert(c, 16'b0000000000000000) `assert(d, 16'b0000000000000000)
        in = 16'b1110000010001010; sel = 2'b11; #1;
         `assert(a, 16'b0000000000000000) `assert(b, 16'b0000000000000000) `assert(c, 16'b0000000000000000) `assert(d, 16'b1110000010001010)
        in = 16'b1110001110010101; sel = 2'b01; #1;
         `assert(a, 16'b0000000000000000) `assert(b, 16'b1110001110010101) `assert(c, 16'b0000000000000000) `assert(d, 16'b0000000000000000)
        in = 16'b1111011111000000; sel = 2'b10; #1;
         `assert(a, 16'b0000000000000000) `assert(b, 16'b0000000000000000) `assert(c, 16'b1111011111000000) `assert(d, 16'b0000000000000000)
        in = 16'b1111110010110001; sel = 2'b11; #1;
         `assert(a, 16'b0000000000000000) `assert(b, 16'b0000000000000000) `assert(c, 16'b0000000000000000) `assert(d, 16'b1111110010110001)
        in = 16'b1111111111111111; sel = 2'b11; #1;
         `assert(a, 16'b0000000000000000) `assert(b, 16'b0000000000000000) `assert(c, 16'b0000000000000000) `assert(d, 16'b1111111111111111)

    end
endmodule

Elementos de Sistemas Computacionais/tb_DMux4Way16.vcd
$date
	Sun Apr 23 11:25:01 2023
$end
$version
	Icarus Verilog
$end
$timescale
	1s
$end
$scope module tb_DMux4Way16 $end
$var wire 16 ! d [15:0] $end
$var wire 16 " c [15:0] $end
$var wire 16 # b [15:0] $end
$var wire 16 $ a [15:0] $end
$var reg 16 % in [15:0] $end
$var reg 2 & sel [1:0] $end
$scope module mymodule $end
$var wire 16 ' in [15:0] $end
$var wire 2 ( sel [1:0] $end
$var wire 16 ) w1 [15:0] $end
$var wire 16 * w0 [15:0] $end
$var wire 16 + d [15:0] $end
$var wire 16 , c [15:0] $end
$var wire 16 - b [15:0] $end
$var wire 16 . a [15:0] $end
$scope module dmux16_0 $end
$var wire 16 / in [15:0] $end
$var wire 1 0 sel $end
$var wire 16 1 b [15:0] $end
$var wire 16 2 a [15:0] $end
$scope module dmux16_0 $end
$var wire 1 3 a $end
$var wire 1 4 b $end
$var wire 1 5 in $end
$var wire 1 0 sel $end
$var wire 1 6 w0 $end
$upscope $end
$scope module dmux16_1 $end
$var wire 1 7 a $end
$var wire 1 8 b $end
$var wire 1 9 in $end
$var wire 1 0 sel $end
$var wire 1 : w0 $end
$upscope $end
$scope module dmux16_10 $end
$var wire 1 ; a $end
$var wire 1 < b $end
$var wire 1 = in $end
$var wire 1 0 sel $end
$var wire 1 > w0 $end
$upscope $end
$scope module dmux16_11 $end
$var wire 1 ? a $end
$var wire 1 @ b $end
$var wire 1 A in $end
$var wire 1 0 sel $end
$var wire 1 B w0 $end
$upscope $end
$scope module dmux16_12 $end
$var wire 1 C a $end
$var wire 1 D b $end
$var wire 1 E in $end
$var wire 1 0 sel $end
$var wire 1 F w0 $end
$upscope $end
$scope module dmux16_13 $end
$var wire 1 G a $end
$var wire 1 H b $end
$var wire 1 I in $end
$var wire 1 0 sel $end
$var wire 1 J w0 $end
$upscope $end
$scope module dmux16_14 $end
$var wire 1 K a $end
$var wire 1 L b $end
$var wire 1 M in $end
$var wire 1 0 sel $end
$var wire 1 N w0 $end
$upscope $end
$scope module dmux16_15 $end
$var wire 1 O a $end
$var wire 1 P b $end
$var wire 1 Q in $end
$var wire 1 0 sel $end
$var wire 1 R w0 $end
$upscope $end
$scope module dmux16_2 $end
$var wire 1 S a $end
$var wire 1 T b $end
$var wire 1 U in $end
$var wire 1 0 sel $end
$var wire 1 V w0 $end
$upscope $end
$scope module dmux16_3 $end
$var wire 1 W a $end
$var wire 1 X b $end
$var wire 1 Y in $end
$var wire 1 0 sel $end
$var wire 1 Z w0 $end
$upscope $end
$scope module dmux16_4 $end
$var wire 1 [ a $end
$var wire 1 \ b $end
$var wire 1 ] in $end
$var wire 1 0 sel $end
$var wire 1 ^ w0 $end
$upscope $end
$scope module dmux16_5 $end
$var wire 1 _ a $end
$var wire 1 ` b $end
$var wire 1 a in $end
$var wire 1 0 sel $end
$var wire 1 b w0 $end
$upscope $end
$scope module dmux16_6 $end
$var wire 1 c a $end
$var wire 1 d b $end
$var wire 1 e in $end
$var wire 1 0 sel $end
$var wire 1 f w0 $end
$upscope $end
$scope module dmux16_7 $end
$var wire 1 g a $end
$var wire 1 h b $end
$var wire 1 i in $end
$var wire 1 0 sel $end
$var wire 1 j w0 $end
$upscope $end
$scope module dmux16_8 $end
$var wire 1 k a $end
$var wire 1 l b $end
$var wire 1 m in $end
$var wire 1 0 sel $end
$var wire 1 n w0 $end
$upscope $end
$scope module dmux16_9 $end
$var wire 1 o a $end
$var wire 1 p b $end
$var wire 1 q in $end
$var wire 1 0 sel $end
$var wire 1 r w0 $end
$upscope $end
$upscope $end
$scope module dmux16_1 $end
$var wire 16 s in [15:0] $end
$var wire 1 t sel $end
$var wire 16 u b [15:0] $end
$var wire 16 v a [15:0] $end
$scope module dmux16_0 $end
$var wire 1 w a $end
$var wire 1 x b $end
$var wire 1 y in $end
$var wire 1 t sel $end
$var wire 1 z w0 $end
$upscope $end
$scope module dmux16_1 $end
$var wire 1 { a $end
$var wire 1 | b $end
$var wire 1 } in $end
$var wire 1 t sel $end
$var wire 1 ~ w0 $end
$upscope $end
$scope module dmux16_10 $end
$var wire 1 !" a $end
$var wire 1 "" b $end
$var wire 1 #" in $end
$var wire 1 t sel $end
$var wire 1 $" w0 $end
$upscope $end
$scope module dmux16_11 $end
$var wire 1 %" a $end
$var wire 1 &" b $end
$var wire 1 '" in $end
$var wire 1 t sel $end
$var wire 1 (" w0 $end
$upscope $end
$scope module dmux16_12 $end
$var wire 1 )" a $end
$var wire 1 *" b $end
$var wire 1 +" in $end
$var wire 1 t sel $end
$var wire 1 ," w0 $end
$upscope $end
$scope module dmux16_13 $end
$var wire 1 -" a $end
$var wire 1 ." b $end
$var wire 1 /" in $end
$var wire 1 t sel $end
$var wire 1 0" w0 $end
$upscope $end
$scope module dmux16_14 $end
$var wire 1 1" a $end
$var wire 1 2" b $end
$var wire 1 3" in $end
$var wire 1 t sel $end
$var wire 1 4" w0 $end
$upscope $end
$scope module dmux16_15 $end
$var wire 1 5" a $end
$var wire 1 6" b $end
$var wire 1 7" in $end
$var wire 1 t sel $end
$var wire 1 8" w0 $end
$upscope $end
$scope module dmux16_2 $end
$var wire 1 9" a $end
$var wire 1 :" b $end
$var wire 1 ;" in $end
$var wire 1 t sel $end
$var wire 1 <" w0 $end
$upscope $end
$scope module dmux16_3 $end
$var wire 1 =" a $end
$var wire 1 >" b $end
$var wire 1 ?" in $end
$var wire 1 t sel $end
$var wire 1 @" w0 $end
$upscope $end
$scope module dmux16_4 $end
$var wire 1 A" a $end
$var wire 1 B" b $end
$var wire 1 C" in $end
$var wire 1 t sel $end
$var wire 1 D" w0 $end
$upscope $end
$scope module dmux16_5 $end
$var wire 1 E" a $end
$var wire 1 F" b $end
$var wire 1 G" in $end
$var wire 1 t sel $end
$var wire 1 H" w0 $end
$upscope $end
$scope module dmux16_6 $end
$var wire 1 I" a $end
$var wire 1 J" b $end
$var wire 1 K" in $end
$var wire 1 t sel $end
$var wire 1 L" w0 $end
$upscope $end
$scope module dmux16_7 $end
$var wire 1 M" a $end
$var wire 1 N" b $end
$var wire 1 O" in $end
$var wire 1 t sel $end
$var wire 1 P" w0 $end
$upscope $end
$scope module dmux16_8 $end
$var wire 1 Q" a $end
$var wire 1 R" b $end
$var wire 1 S" in $end
$var wire 1 t sel $end
$var wire 1 T" w0 $end
$upscope $end
$scope module dmux16_9 $end
$var wire 1 U" a $end
$var wire 1 V" b $end
$var wire 1 W" in $end
$var wire 1 t sel $end
$var wire 1 X" w0 $end
$upscope $end
$upscope $end
$scope module dmux16_2 $end
$var wire 16 Y" in [15:0] $end
$var wire 1 Z" sel $end
$var wire 16 [" b [15:0] $end
$var wire 16 \" a [15:0] $end
$scope module dmux16_0 $end
$var wire 1 ]" a $end
$var wire 1 ^" b $end
$var wire 1 _" in $end
$var wire 1 Z" sel $end
$var wire 1 `" w0 $end
$upscope $end
$scope module dmux16_1 $end
$var wire 1 a" a $end
$var wire 1 b" b $end
$var wire 1 c" in $end
$var wire 1 Z" sel $end
$var wire 1 d" w0 $end
$upscope $end
$scope module dmux16_10 $end
$var wire 1 e" a $end
$var wire 1 f" b $end
$var wire 1 g" in $end
$var wire 1 Z" sel $end
$var wire 1 h" w0 $end
$upscope $end
$scope module dmux16_11 $end
$var wire 1 i" a $end
$var wire 1 j" b $end
$var wire 1 k" in $end
$var wire 1 Z" sel $end
$var wire 1 l" w0 $end
$upscope $end
$scope module dmux16_12 $end
$var wire 1 m" a $end
$var wire 1 n" b $end
$var wire 1 o" in $end
$var wire 1 Z" sel $end
$var wire 1 p" w0 $end
$upscope $end
$scope module dmux16_13 $end
$var wire 1 q" a $end
$var wire 1 r" b $end
$var wire 1 s" in $end
$var wire 1 Z" sel $end
$var wire 1 t" w0 $end
$upscope $end
$scope module dmux16_14 $end
$var wire 1 u" a $end
$var wire 1 v" b $end
$var wire 1 w" in $end
$var wire 1 Z" sel $end
$var wire 1 x" w0 $end
$upscope $end
$scope module dmux16_15 $end
$var wire 1 y" a $end
$var wire 1 z" b $end
$var wire 1 {" in $end
$var wire 1 Z" sel $end
$var wire 1 |" w0 $end
$upscope $end
$scope module dmux16_2 $end
$var wire 1 }" a $end
$var wire 1 ~" b $end
$var wire 1 !# in $end
$var wire 1 Z" sel $end
$var wire 1 "# w0 $end
$upscope $end
$scope module dmux16_3 $end
$var wire 1 ## a $end
$var wire 1 $# b $end
$var wire 1 %# in $end
$var wire 1 Z" sel $end
$var wire 1 &# w0 $end
$upscope $end
$scope module dmux16_4 $end
$var wire 1 '# a $end
$var wire 1 (# b $end
$var wire 1 )# in $end
$var wire 1 Z" sel $end
$var wire 1 *# w0 $end
$upscope $end
$scope module dmux16_5 $end
$var wire 1 +# a $end
$var wire 1 ,# b $end
$var wire 1 -# in $end
$var wire 1 Z" sel $end
$var wire 1 .# w0 $end
$upscope $end
$scope module dmux16_6 $end
$var wire 1 /# a $end
$var wire 1 0# b $end
$var wire 1 1# in $end
$var wire 1 Z" sel $end
$var wire 1 2# w0 $end
$upscope $end
$scope module dmux16_7 $end
$var wire 1 3# a $end
$var wire 1 4# b $end
$var wire 1 5# in $end
$var wire 1 Z" sel $end
$var wire 1 6# w0 $end
$upscope $end
$scope module dmux16_8 $end
$var wire 1 7# a $end
$var wire 1 8# b $end
$var wire 1 9# in $end
$var wire 1 Z" sel $end
$var wire 1 :# w0 $end
$upscope $end
$scope module dmux16_9 $end
$var wire 1 ;# a $end
$var wire 1 <# b $end
$var wire 1 =# in $end
$var wire 1 Z" sel $end
$var wire 1 ># w0 $end
$upscope $end
$upscope $end
$upscope $end
$upscope $end
$enddefinitions $end
$comment Show the parameter values. $end
$dumpall
$end
#0
$dumpvars
1>#
0=#
0<#
0;#
1:#
09#
08#
07#
16#
05#
04#
03#
12#
01#
00#
0/#
1.#
0-#
0,#
0+#
1*#
0)#
0(#
0'#
1&#
0%#
0$#
0##
1"#
0!#
0~"
0}"
1|"
0{"
0z"
0y"
1x"
0w"
0v"
0u"
1t"
0s"
0r"
0q"
1p"
0o"
0n"
0m"
1l"
0k"
0j"
0i"
1h"
0g"
0f"
0e"
1d"
0c"
0b"
0a"
1`"
0_"
0^"
0]"
b0 \"
b0 ["
0Z"
b0 Y"
1X"
0W"
0V"
0U"
1T"
0S"
0R"
0Q"
1P"
0O"
0N"
0M"
1L"
0K"
0J"
0I"
1H"
0G"
0F"
0E"
1D"
0C"
0B"
0A"
1@"
0?"
0>"
0="
1<"
0;"
0:"
09"
18"
07"
06"
05"
14"
03"
02"
01"
10"
0/"
0."
0-"
1,"
0+"
0*"
0)"
1("
0'"
0&"
0%"
1$"
0#"
0""
0!"
1~
0}
0|
0{
1z
0y
0x
0w
b0 v
b0 u
0t
b0 s
1r
0q
0p
0o
1n
0m
0l
0k
1j
0i
0h
0g
1f
0e
0d
0c
1b
0a
0`
0_
1^
0]
0\
0[
1Z
0Y
0X
0W
1V
0U
0T
0S
1R
0Q
0P
0O
1N
0M
0L
0K
1J
0I
0H
0G
1F
0E
0D
0C
1B
0A
0@
0?
1>
0=
0<
0;
1:
09
08
07
16
05
04
03
b0 2
b0 1
00
b0 /
b0 .
b0 -
b0 ,
b0 +
b0 *
b0 )
b0 (
b0 '
b0 &
b0 %
b0 $
b0 #
b0 "
b0 !
$end
#1
1|
1>"
1B"
1F"
1R"
b1100111010 #
b1100111010 -
b1100111010 u
1V"
1}
1?"
1C"
1G"
1S"
1W"
0z
0~
0$"
0("
0,"
00"
04"
08"
0<"
0@"
0D"
0H"
0L"
0P"
0T"
0X"
0`"
0d"
0h"
0l"
0p"
0t"
0x"
0|"
0"#
0&#
0*#
0.#
02#
06#
0:#
0>#
17
1W
1[
1_
1k
b1100111010 *
b1100111010 2
b1100111010 s
1o
1t
1Z"
19
1Y
1]
1a
1m
1q
b1 &
b1 (
b1100111010 %
b1100111010 '
b1100111010 /
#2
1a"
0}
1+#
0G"
1c"
07
1-#
0_
0{
0!"
09"
b0 $
b0 .
b0 v
0E"
1e"
b10000100110 "
b10000100110 ,
b10000100110 \"
1}"
1!#
0;"
0?"
0C"
0S"
0W"
1g"
0#"
06
18
0:
0>
0B
0F
0J
0N
0R
0V
0Z
0^
1`
0b
0f
0j
0n
0r
1z
0|
1~
1$"
1("
1,"
10"
14"
18"
1<"
0>"
1@"
0B"
1D"
0F"
1H"
1L"
1P"
0R"
1T"
b0 #
b0 -
b0 u
0V"
1X"
1`"
1d"
1h"
1l"
1p"
1t"
1x"
1|"
1"#
1&#
1*#
1.#
12#
16#
1:#
1>#
1T
0S
0W
0[
0k
0o
b10000100110 )
b10000100110 1
b10000100110 Y"
1<
b0 *
b0 2
b0 s
0;
10
0t
0Z"
1U
0Y
0]
0m
0q
1=
b10 &
b10 (
b10000100110 %
b10000100110 '
b10000100110 /
#3
1x
1|
1""
1&"
1*"
1:"
1B"
1N"
b1110110010111 #
b1110110010111 -
b1110110010111 u
1R"
1y
1}
1#"
1'"
1+"
1;"
1C"
1O"
1S"
13
0c"
17
0g"
1;
1?
1C
0!#
1S
1[
1g
b1110110010111 *
b1110110010111 2
b1110110010111 s
1k
0a"
0e"
0}"
b0 "
b0 ,
b0 \"
0+#
0-#
16
08
1:
0<
1>
1B
1F
1J
1N
1R
0T
1V
1Z
1^
1b
1f
1j
1n
1r
0z
0~
0$"
0("
0,"
00"
04"
08"
0<"
0@"
0D"
0H"
0L"
0P"
0T"
0X"
0`"
0b"
0d"
0f"
0h"
0l"
0p"
0t"
0x"
0|"
0~"
0"#
0&#
0*#
b0 !
b0 +
b0 ["
0,#
0.#
02#
06#
0:#
0>#
b0 )
b0 1
b0 Y"
0`
00
1t
1Z"
15
1]
0a
1i
1m
1A
1E
b1 &
b1 (
b1110110010111 %
b1110110010111 '
b1110110010111 /
#4
0|
0:"
1>"
1J"
0N"
1V"
0""
0&"
0*"
b10001101011001 #
b10001101011001 -
b10001101011001 u
1."
0}
0;"
1?"
1K"
0O"
1W"
0#"
0'"
0+"
1/"
07
0S
1W
1c
0g
1o
0;
0?
0C
b10001101011001 *
b10001101011001 2
b10001101011001 s
1G
09
0U
1Y
1e
0i
1q
0=
0A
0E
1I
b10001101011001 %
b10001101011001 '
b10001101011001 /
#5
1!"
1-"
1E"
1I"
1M"
1Q"
b10011111100000 $
b10011111100000 .
b10011111100000 v
1U"
0y
0?"
0C"
1G"
1O"
1#"
0x
1z
1~
1$"
1("
1,"
0."
10"
14"
18"
1<"
0>"
1@"
0B"
1D"
1H"
0J"
1L"
1P"
0R"
1T"
b0 #
b0 -
b0 u
0V"
1X"
1`"
1d"
1h"
1l"
1p"
1t"
1x"
1|"
1"#
1&#
1*#
1.#
12#
16#
1:#
1>#
03
0W
0[
1_
1g
b10011111100000 *
b10011111100000 2
b10011111100000 s
1;
0t
0Z"
05
0Y
0]
1a
1i
1=
b0 &
b0 (
b10011111100000 %
b10011111100000 '
b10011111100000 /
#6
0!"
0-"
0U"
1e"
0#"
1q"
0/"
1;#
0W"
1]"
0w
0E"
0I"
0M"
0Q"
b10111000000001 "
b10111000000001 ,
b10111000000001 \"
1i"
b0 $
b0 .
b0 v
0%"
1g"
0;
1s"
0G
1=#
0o
1_"
0y
0G"
0K"
0O"
0S"
1k"
0'"
06
0:
1<
0>
0B
0F
1H
0J
0N
0R
0V
0Z
0^
0b
0f
0j
0n
1p
0r
14
03
0_
0c
0g
0k
b10111000000001 )
b10111000000001 1
b10111000000001 Y"
1@
b0 *
b0 2
b0 s
0?
10
15
0a
0e
0i
0m
1A
b10 &
b10 (
b10111000000001 %
b10111000000001 '
b10111000000001 /
#7
1}"
1+#
1/#
17#
0;#
0e"
b11100101100101 "
b11100101100101 ,
b11100101100101 \"
1m"
1!#
1-#
11#
19#
0=#
0g"
1o"
1T
1`
1d
1l
0p
0<
b11100101100101 )
b11100101100101 1
b11100101100101 Y"
1D
1U
1a
1e
1m
0q
0=
1E
b11100101100101 %
b11100101100101 '
b11100101100101 /
#8
1b"
1$#
14#
1f"
0]"
0i"
0m"
0q"
0}"
0+#
0/#
b0 "
b0 ,
b0 \"
07#
1c"
1%#
0-#
15#
09#
1g"
0z
0~
0$"
0("
0,"
00"
04"
08"
0<"
0@"
0D"
0H"
0L"
0P"
0T"
0X"
1^"
0`"
0d"
0h"
1j"
0l"
1n"
0p"
1r"
0t"
0x"
0|"
1~"
0"#
0&#
0*#
0,#
0.#
10#
02#
06#
b11110011001111 !
b11110011001111 +
b11110011001111 ["
08#
0:#
0>#
18
1X
0`
1h
0l
b11110011001111 )
b11110011001111 1
b11110011001111 Y"
1<
1t
1Z"
19
1Y
0a
1i
0m
1=
b11 &
b11 (
b11110011001111 %
b11110011001111 '
b11110011001111 /
#9
1%"
11"
1E"
1M"
b100100110100000 $
b100100110100000 .
b100100110100000 v
1Q"
1'"
13"
1G"
1O"
1S"
0k"
1?
1K
1_
05#
1g
b100100110100000 *
b100100110100000 2
b100100110100000 s
1k
0i"
b0 "
b0 ,
b0 \"
03#
0_"
0c"
0!#
0%#
01#
0g"
0o"
0s"
16
1:
1>
0@
1B
1F
1J
1N
1R
1V
1Z
1^
1b
1f
0h
1j
1n
1r
1z
1~
1$"
1("
1,"
10"
14"
18"
1<"
1@"
1D"
1H"
1L"
1P"
1T"
1X"
0^"
1`"
0b"
1d"
0f"
1h"
0j"
1l"
0n"
1p"
0r"
1t"
1x"
1|"
0~"
1"#
0$#
1&#
1*#
1.#
00#
12#
b0 !
b0 +
b0 ["
04#
16#
1:#
1>#
04
08
0T
0X
0d
0<
0D
b0 )
b0 1
b0 Y"
0H
00
0t
0Z"
05
09
0U
0Y
1a
0e
1m
0=
0E
0I
1M
b0 &
b0 (
b100100110100000 %
b100100110100000 '
b100100110100000 /
#10
1|
1>"
1V"
1""
0%"
01"
0E"
0M"
b0 $
b0 .
b0 v
0Q"
1}
1?"
0S"
1W"
1#"
0z
0~
0$"
1&"
0("
0,"
00"
12"
04"
08"
0<"
0@"
0D"
1F"
0H"
0L"
1N"
0P"
b100111010101010 #
b100111010101010 -
b100111010101010 u
0R"
0T"
0X"
0`"
0d"
0h"
0l"
0p"
0t"
0x"
0|"
0"#
0&#
0*#
0.#
02#
06#
0:#
0>#
17
1W
0k
1o
b100111010101010 *
b100111010101010 2
b100111010101010 s
1;
1t
1Z"
19
1Y
0m
1q
1=
b1 &
b1 (
b100111010101010 %
b100111010101010 '
b100111010101010 /
#11
1{
1%"
1)"
11"
19"
b101100000100110 $
b101100000100110 .
b101100000100110 v
1E"
1;"
0?"
0O"
0W"
0#"
1+"
1z
0|
1~
0""
1$"
0&"
1("
1,"
10"
02"
14"
18"
1<"
0>"
1@"
1D"
0F"
1H"
1L"
0N"
1P"
1T"
b0 #
b0 -
b0 u
0V"
1X"
1`"
1d"
1h"
1l"
1p"
1t"
1x"
1|"
1"#
1&#
1*#
1.#
12#
16#
1:#
1>#
1S
0W
0g
0o
0;
b101100000100110 *
b101100000100110 2
b101100000100110 s
1C
0t
0Z"
1U
0Y
0i
0q
0=
1E
b0 &
b0 (
b101100000100110 %
b101100000100110 '
b101100000100110 /
#12
1j"
0'"
1n"
0+"
1v"
03"
1~"
0;"
1,#
0G"
1^"
0x
1$#
0>"
14#
0N"
18#
0R"
1<#
0V"
b101111110101101 !
b101111110101101 +
b101111110101101 ["
1f"
0""
1k"
0?
1o"
0C
1w"
0K
1!#
0S
1-#
0_
0{
0%"
0)"
01"
09"
b0 $
b0 .
b0 v
0E"
1_"
0y
0}
1%#
0?"
15#
0O"
19#
0S"
1=#
0W"
1g"
0#"
06
0:
0>
1@
0B
1D
0F
0J
1L
0N
0R
1T
0V
0Z
0^
1`
0b
0f
0j
0n
0r
0z
0|
0~
0$"
0&"
0("
0*"
0,"
00"
02"
04"
08"
0:"
0<"
0@"
0D"
b0 #
b0 -
b0 u
0F"
0H"
0L"
0P"
0T"
0X"
0`"
0d"
0h"
0l"
0p"
0t"
0x"
0|"
0"#
0&#
0*#
0.#
02#
06#
0:#
0>#
14
03
07
1X
0W
1h
0g
1l
0k
1p
0o
b101111110101101 )
b101111110101101 1
b101111110101101 Y"
1<
b0 *
b0 2
b0 s
0;
10
1t
1Z"
15
09
1Y
1i
1m
1q
1=
b11 &
b11 (
b101111110101101 %
b101111110101101 '
b101111110101101 /
#13
1x
1&"
1."
12"
1:"
1B"
1F"
1N"
1R"
b110101110110101 #
b110101110110101 -
b110101110110101 u
1V"
0^"
1y
0j"
1'"
1/"
0v"
13"
0~"
1;"
1C"
0,#
1G"
04#
1O"
08#
1S"
0<#
1W"
0$#
0f"
b0 !
b0 +
b0 ["
0n"
0_"
13
0k"
1?
1G
0w"
1K
0!#
1S
1[
0-#
1_
05#
1g
09#
1k
0=#
b110101110110101 *
b110101110110101 2
b110101110110101 s
1o
0%#
0g"
0o"
04
16
1:
1>
0@
1B
1F
1J
0L
1N
1R
0T
1V
1Z
1^
0`
1b
1f
0h
1j
0l
1n
0p
1r
0X
0<
b0 )
b0 1
b0 Y"
0D
00
0Y
1]
0=
0E
1I
b1 &
b1 (
b110101110110101 %
b110101110110101 '
b110101110110101 /
