Elementos de Sistemas Computacionais/DLatch.v
/* módulo DLatch */

`ifndef _DLatch_
`define _DLatch_

module DLatch(q, d, clk);
    input d, clk;
    output q;
    wire w1, w2, w3, w4, w5, w6, w7, w8, w9, nq;

    nand nand1(w2, d, clk);
    not not1(w1, d);
    nand nand2(w5, w2, w3);
    nand nand3(w4, clk, w1);
    nand nand4(w3, w5, w4);
    not not2(w7, clk);
    not not3(w6, w5);
    nand nand5(w8, w5, w7);
    nand nand6(q, w8, nq);
    nand nand7(w9, w7, w6);
    nand nand8(nq, q, w9);

    // Descrição de conexões internas do módulo

endmodule

`endif

Elementos de Sistemas Computacionais/tb_DLatch.v
/* testbench para DLatch */
/* ordem de portas: q, d, clk */
/* input d, clk; */
/* output q; */

`include "DLatch.v"

`define assert(signal, value) \
    if (signal !== value) \
    begin \
        $display("ASSERTION FAILED in %m: signal != value"); \
        $finish; \
    end else begin \
        $display("Success! %m: signal = value"); \
    end

module tb_DLatch;
    reg d, clk;
    wire q;

    DLatch dlatch0(q, d, clk);
    
    always
    begin
        #1 clk = ~clk;
    end
    
    initial
    begin
        $dumpfile("tb_DLatch.vcd");
        $dumpvars(0, tb_DLatch);

        clk = 0;

        d = 0; #3;
        `assert(q, 1'b0)

        d = 1; #3;
        `assert(q, 1'b1)

        d = 1; #3;
        `assert(q, 1'b1)

        d = 0; #3;
        `assert(q, 1'b0)

        d = 0; #3;
        `assert(q, 1'b0)

        $finish;
    end

endmodule

Elementos de Sistemas Computacionais/tb_DLatch.vcd
$date
	Sun Apr 23 11:32:04 2023
$end
$version
	Icarus Verilog
$end
$timescale
	1s
$end
$scope module tb_DLatch $end
$var wire 1 ! q $end
$var reg 1 " clk $end
$var reg 1 # d $end
$scope module dlatch0 $end
$var wire 1 " clk $end
$var wire 1 # d $end
$var wire 1 $ nq $end
$var wire 1 ! q $end
$var wire 1 % w1 $end
$var wire 1 & w2 $end
$var wire 1 ' w3 $end
$var wire 1 ( w4 $end
$var wire 1 ) w5 $end
$var wire 1 * w6 $end
$var wire 1 + w7 $end
$var wire 1 , w8 $end
$var wire 1 - w9 $end
$upscope $end
$upscope $end
$enddefinitions $end
$comment Show the parameter values. $end
$dumpall
$end
#0
$dumpvars
x-
x,
1+
x*
x)
1(
x'
1&
1%
x$
0#
0"
x!
$end
#1
1*
0)
1'
1,
1-
0(
0+
1"
#2
0!
1$
0-
1(
1+
0"
#3
0'
0*
1-
1)
0+
0&
0%
1"
1#
#4
0$
1!
0,
1&
1+
0"
#5
1,
0&
0+
1"
#6
0,
1&
1+
0"
#7
1,
0&
0+
1"
#8
0,
1&
1+
0"
#9
1*
0)
1'
1,
0(
0+
1%
1"
0#
#10
0!
1$
0-
1(
1+
0"
#11
1-
0(
0+
1"
#12
0-
1(
1+
0"
#13
1-
0(
0+
1"
#14
0-
1(
1+
0"
#15
1-
0(
0+
1"
