Elementos de Sistemas Computacionais/Tarefa01_12011ECP008GabrielAlves/HalfAdder.v
/* módulo HalfAdder */

`ifndef _HalfAdder_
`define _HalfAdder_

module HalfAdder(s, c, a, b);
    input a, b;
    output s, c;

    xor xor0(s, a, b);
    and and0(c, a, b);
endmodule

`endif

Elementos de Sistemas Computacionais/FullAdder.v
/* módulo FullAdder */

`ifndef _FullAdder_
`define _FullAdder_
`include "HalfAdder.v"

module FullAdder(s, cout, a, b, cin);
    input a, b, cin;
    output cout, s;
    wire w0, w1, w2;

    HalfAdder ha0(w1, w0, a, b);
    HalfAdder ha1(s, w2, w1, cin);
    or or0(cout, w0, w2);

    // Descrição de conexões internas do módulo

endmodule

`endif

Elementos de Sistemas Computacionais/tb_FullAdder.v
/* testbench para FullAdder */
/* ordem de portas: s, cout, a, b, cin */
/* input a; input b; input cin; */
/* output s; output cout; */

`include "FullAdder.v"

`define assert(signal, value) \
    if (signal !== value) \
    begin \
        $display("ASSERTION FAILED in %m: signal != value"); \
        $finish; \
    end else begin \
        $display("Success! %m: signal = value"); \
    end

module tb_FullAdder;
    reg a;
    reg b;
    reg cin;
    wire s;
    wire cout;

    FullAdder mymodule(s, cout, a, b, cin);
    
    initial
    begin
        $dumpfile("tb_FullAdder.vcd");
        $dumpvars(0, tb_FullAdder);

        a = 1'b0; b = 1'b0; cin = 1'b0; #1;
         `assert(s, 1'b0) `assert(cout, 1'b0)
        a = 1'b0; b = 1'b0; cin = 1'b1; #1;
         `assert(s, 1'b1) `assert(cout, 1'b0)
        a = 1'b0; b = 1'b1; cin = 1'b0; #1;
         `assert(s, 1'b1) `assert(cout, 1'b0)
        a = 1'b0; b = 1'b1; cin = 1'b1; #1;
         `assert(s, 1'b0) `assert(cout, 1'b1)
        a = 1'b1; b = 1'b0; cin = 1'b0; #1;
         `assert(s, 1'b1) `assert(cout, 1'b0)
        a = 1'b1; b = 1'b0; cin = 1'b1; #1;
         `assert(s, 1'b0) `assert(cout, 1'b1)
        a = 1'b1; b = 1'b1; cin = 1'b0; #1;
         `assert(s, 1'b0) `assert(cout, 1'b1)
        a = 1'b1; b = 1'b1; cin = 1'b1; #1;
         `assert(s, 1'b1) `assert(cout, 1'b1)

    end
endmodule

Elementos de Sistemas Computacionais/tb_FullAdder.vcd
$date
	Thu Apr 20 13:54:00 2023
$end
$version
	Icarus Verilog
$end
$timescale
	1s
$end
$scope module tb_FullAdder $end
$var wire 1 ! s $end
$var wire 1 " cout $end
$var reg 1 # a $end
$var reg 1 $ b $end
$var reg 1 % cin $end
$scope module mymodule $end
$var wire 1 # a $end
$var wire 1 $ b $end
$var wire 1 % cin $end
$var wire 1 " cout $end
$var wire 1 & w2 $end
$var wire 1 ' w1 $end
$var wire 1 ( w0 $end
$var wire 1 ! s $end
$scope module ha0 $end
$var wire 1 # a $end
$var wire 1 $ b $end
$var wire 1 ( c $end
$var wire 1 ' s $end
$upscope $end
$scope module ha1 $end
$var wire 1 ' a $end
$var wire 1 % b $end
$var wire 1 & c $end
$var wire 1 ! s $end
$upscope $end
$upscope $end
$upscope $end
$enddefinitions $end
$comment Show the parameter values. $end
$dumpall
$end
#0
$dumpvars
0(
0'
0&
0%
0$
0#
0"
0!
$end
#1
1!
1%
#2
1'
0%
1$
#3
1"
0!
1&
1%
#4
0"
1!
0&
0%
0$
1#
#5
1"
0!
1&
1%
#6
0&
0'
1(
0%
1$
#7
1!
1%
