Elementos de Sistemas Computacionais/Mux.v
/* módulo Mux */

`ifndef _Mux_
`define _Mux_

module Mux(out, a, b, sel);
    input a, b, sel;
    output out;
    wire w0, w1, w2;

    
    nand nand0(w0, a, w2);
    nand nand1(w1, b, sel);
    nand nand2(out, w0, w1);
    not not0(w2, sel);

    // Descrição de conexões internas do módulo

endmodule

`endif

Elementos de Sistemas Computacionais/Mux16.v
/* módulo Mux16 */

`ifndef _Mux16_
`define _Mux16_

`include "Mux.v"

module Mux16(out, a, b, sel);
    input [15:0] a, b;
    input sel;
    output [15:0] out;

    Mux mux16_0(out[0], a[0], b[0], sel);
    Mux mux16_1(out[1], a[1], b[1], sel);
    Mux mux16_2(out[2], a[2], b[2], sel);
    Mux mux16_3(out[3], a[3], b[3], sel);
    Mux mux16_4(out[4], a[4], b[4], sel);
    Mux mux16_5(out[5], a[5], b[5], sel);
    Mux mux16_6(out[6], a[6], b[6], sel);
    Mux mux16_7(out[7], a[7], b[7], sel);
    Mux mux16_8(out[8], a[8], b[8], sel);
    Mux mux16_9(out[9], a[9], b[9], sel);
    Mux mux16_10(out[10], a[10], b[10], sel);
    Mux mux16_11(out[11], a[11], b[11], sel);
    Mux mux16_12(out[12], a[12], b[12], sel);
    Mux mux16_13(out[13], a[13], b[13], sel);
    Mux mux16_14(out[14], a[14], b[14], sel);
    Mux mux16_15(out[15], a[15], b[15], sel);





    // Descrição de conexões internas do módulo

endmodule

`endif

Elementos de Sistemas Computacionais/tb_Mux16.v
/* testbench para Mux16 */
/* ordem de portas: out, a, b, sel */
/* input [15:0] a; input [15:0] b; input sel; */
/* output [15:0] out; */

`include "Mux16.v"

`define assert(signal, value) \
    if (signal !== value) \
    begin \
        $display("ASSERTION FAILED in %m: signal != value"); \
        $finish; \
    end else begin \
        $display("Success! %m: signal = value"); \
    end

module tb_Mux16;
    reg [15:0] a;
    reg [15:0] b;
    reg sel;
    wire [15:0] out;

    Mux16 mymodule(out, a, b, sel);
    
    initial
    begin
        $dumpfile("tb_Mux16.vcd");
        $dumpvars(0, tb_Mux16);

        a = 16'b0000110011000011; b = 16'b0000000001111010; sel = 1'b1; #1;
         `assert(out, 16'b0000000001111010)
        a = 16'b0000111000001111; b = 16'b0000100000110110; sel = 1'b0; #1;
         `assert(out, 16'b0000111000001111)
        a = 16'b0001100100001100; b = 16'b0100110001101000; sel = 1'b0; #1;
         `assert(out, 16'b0001100100001100)
        a = 16'b0001101001100011; b = 16'b1001111001010110; sel = 1'b0; #1;
         `assert(out, 16'b0001101001100011)
        a = 16'b0001111111001111; b = 16'b0011001001010101; sel = 1'b1; #1;
         `assert(out, 16'b0011001001010101)
        a = 16'b0011111010001001; b = 16'b1010000100000111; sel = 1'b1; #1;
         `assert(out, 16'b1010000100000111)
        a = 16'b0101010010000001; b = 16'b0000100111111010; sel = 1'b0; #1;
         `assert(out, 16'b0101010010000001)
        a = 16'b0101101100011001; b = 16'b1111010101111010; sel = 1'b0; #1;
         `assert(out, 16'b0101101100011001)
        a = 16'b0101101101111000; b = 16'b1000010000000110; sel = 1'b1; #1;
         `assert(out, 16'b1000010000000110)
        a = 16'b0110000101101101; b = 16'b1000001001001011; sel = 1'b1; #1;
         `assert(out, 16'b1000001001001011)
        a = 16'b0110101000000010; b = 16'b0000111001010110; sel = 1'b1; #1;
         `assert(out, 16'b0000111001010110)
        a = 16'b0110110101100010; b = 16'b1010000010001001; sel = 1'b0; #1;
         `assert(out, 16'b0110110101100010)
        a = 16'b1000000000011010; b = 16'b0000110101110110; sel = 1'b1; #1;
         `assert(out, 16'b0000110101110110)
        a = 16'b1000010101010011; b = 16'b1001111000010000; sel = 1'b1; #1;
         `assert(out, 16'b1001111000010000)
        a = 16'b1001000011011000; b = 16'b0001001010101000; sel = 1'b1; #1;
         `assert(out, 16'b0001001010101000)
        a = 16'b1001011000000000; b = 16'b0110000010111011; sel = 1'b1; #1;
         `assert(out, 16'b0110000010111011)
        a = 16'b1001011111100010; b = 16'b1100111111110100; sel = 1'b0; #1;
         `assert(out, 16'b1001011111100010)
        a = 16'b1010000010110101; b = 16'b1011110000111010; sel = 1'b1; #1;
         `assert(out, 16'b1011110000111010)
        a = 16'b1010011111010011; b = 16'b1011000011010011; sel = 1'b0; #1;
         `assert(out, 16'b1010011111010011)
        a = 16'b1010111000111101; b = 16'b1010010000010011; sel = 1'b1; #1;
         `assert(out, 16'b1010010000010011)
        a = 16'b1011001011001010; b = 16'b1010111110101000; sel = 1'b1; #1;
         `assert(out, 16'b1010111110101000)
        a = 16'b1011010010111110; b = 16'b1101011011110011; sel = 1'b1; #1;
         `assert(out, 16'b1101011011110011)
        a = 16'b1011011110111011; b = 16'b1111001111010001; sel = 1'b1; #1;
         `assert(out, 16'b1111001111010001)
        a = 16'b1011111010111110; b = 16'b1001000011000010; sel = 1'b0; #1;
         `assert(out, 16'b1011111010111110)
        a = 16'b1100010010101110; b = 16'b0111011001100010; sel = 1'b0; #1;
         `assert(out, 16'b1100010010101110)
        a = 16'b1101101011101010; b = 16'b1000111001001010; sel = 1'b0; #1;
         `assert(out, 16'b1101101011101010)
        a = 16'b1101101110110101; b = 16'b0011010011100000; sel = 1'b1; #1;
         `assert(out, 16'b0011010011100000)
        a = 16'b1101110000100011; b = 16'b0110001000001111; sel = 1'b1; #1;
         `assert(out, 16'b0110001000001111)
        a = 16'b1110100111001111; b = 16'b1010001100110110; sel = 1'b0; #1;
         `assert(out, 16'b1110100111001111)
        a = 16'b1111000011011110; b = 16'b0100101100011010; sel = 1'b0; #1;
         `assert(out, 16'b1111000011011110)

    end
endmodule

Elementos de Sistemas Computacionais/tb_Mux16.vcd
$date
	Wed May 03 22:03:52 2023
$end
$version
	Icarus Verilog
$end
$timescale
	1s
$end
$scope module tb_Mux16 $end
$var wire 16 ! out [15:0] $end
$var reg 16 " a [15:0] $end
$var reg 16 # b [15:0] $end
$var reg 1 $ sel $end
$scope module mymodule $end
$var wire 16 % a [15:0] $end
$var wire 16 & b [15:0] $end
$var wire 1 $ sel $end
$var wire 16 ' out [15:0] $end
$scope module mux16_0 $end
$var wire 1 ( a $end
$var wire 1 ) b $end
$var wire 1 * out $end
$var wire 1 $ sel $end
$var wire 1 + w0 $end
$var wire 1 , w1 $end
$var wire 1 - w2 $end
$upscope $end
$scope module mux16_1 $end
$var wire 1 . a $end
$var wire 1 / b $end
$var wire 1 0 out $end
$var wire 1 $ sel $end
$var wire 1 1 w0 $end
$var wire 1 2 w1 $end
$var wire 1 3 w2 $end
$upscope $end
$scope module mux16_10 $end
$var wire 1 4 a $end
$var wire 1 5 b $end
$var wire 1 6 out $end
$var wire 1 $ sel $end
$var wire 1 7 w0 $end
$var wire 1 8 w1 $end
$var wire 1 9 w2 $end
$upscope $end
$scope module mux16_11 $end
$var wire 1 : a $end
$var wire 1 ; b $end
$var wire 1 < out $end
$var wire 1 $ sel $end
$var wire 1 = w0 $end
$var wire 1 > w1 $end
$var wire 1 ? w2 $end
$upscope $end
$scope module mux16_12 $end
$var wire 1 @ a $end
$var wire 1 A b $end
$var wire 1 B out $end
$var wire 1 $ sel $end
$var wire 1 C w0 $end
$var wire 1 D w1 $end
$var wire 1 E w2 $end
$upscope $end
$scope module mux16_13 $end
$var wire 1 F a $end
$var wire 1 G b $end
$var wire 1 H out $end
$var wire 1 $ sel $end
$var wire 1 I w0 $end
$var wire 1 J w1 $end
$var wire 1 K w2 $end
$upscope $end
$scope module mux16_14 $end
$var wire 1 L a $end
$var wire 1 M b $end
$var wire 1 N out $end
$var wire 1 $ sel $end
$var wire 1 O w0 $end
$var wire 1 P w1 $end
$var wire 1 Q w2 $end
$upscope $end
$scope module mux16_15 $end
$var wire 1 R a $end
$var wire 1 S b $end
$var wire 1 T out $end
$var wire 1 $ sel $end
$var wire 1 U w0 $end
$var wire 1 V w1 $end
$var wire 1 W w2 $end
$upscope $end
$scope module mux16_2 $end
$var wire 1 X a $end
$var wire 1 Y b $end
$var wire 1 Z out $end
$var wire 1 $ sel $end
$var wire 1 [ w0 $end
$var wire 1 \ w1 $end
$var wire 1 ] w2 $end
$upscope $end
$scope module mux16_3 $end
$var wire 1 ^ a $end
$var wire 1 _ b $end
$var wire 1 ` out $end
$var wire 1 $ sel $end
$var wire 1 a w0 $end
$var wire 1 b w1 $end
$var wire 1 c w2 $end
$upscope $end
$scope module mux16_4 $end
$var wire 1 d a $end
$var wire 1 e b $end
$var wire 1 f out $end
$var wire 1 $ sel $end
$var wire 1 g w0 $end
$var wire 1 h w1 $end
$var wire 1 i w2 $end
$upscope $end
$scope module mux16_5 $end
$var wire 1 j a $end
$var wire 1 k b $end
$var wire 1 l out $end
$var wire 1 $ sel $end
$var wire 1 m w0 $end
$var wire 1 n w1 $end
$var wire 1 o w2 $end
$upscope $end
$scope module mux16_6 $end
$var wire 1 p a $end
$var wire 1 q b $end
$var wire 1 r out $end
$var wire 1 $ sel $end
$var wire 1 s w0 $end
$var wire 1 t w1 $end
$var wire 1 u w2 $end
$upscope $end
$scope module mux16_7 $end
$var wire 1 v a $end
$var wire 1 w b $end
$var wire 1 x out $end
$var wire 1 $ sel $end
$var wire 1 y w0 $end
$var wire 1 z w1 $end
$var wire 1 { w2 $end
$upscope $end
$scope module mux16_8 $end
$var wire 1 | a $end
$var wire 1 } b $end
$var wire 1 ~ out $end
$var wire 1 $ sel $end
$var wire 1 !" w0 $end
$var wire 1 "" w1 $end
$var wire 1 #" w2 $end
$upscope $end
$scope module mux16_9 $end
$var wire 1 $" a $end
$var wire 1 %" b $end
$var wire 1 &" out $end
$var wire 1 $ sel $end
$var wire 1 '" w0 $end
$var wire 1 (" w1 $end
$var wire 1 )" w2 $end
$upscope $end
$upscope $end
$upscope $end
$enddefinitions $end
$comment Show the parameter values. $end
$dumpall
$end
#0
$dumpvars
0)"
1("
1'"
0&"
0%"
0$"
0#"
1""
1!"
0~
0}
0|
0{
1z
1y
0x
0w
1v
0u
0t
1s
1r
1q
1p
0o
0n
1m
1l
1k
0j
0i
0h
1g
1f
1e
0d
0c
0b
1a
1`
1_
0^
0]
1\
1[
0Z
0Y
0X
0W
1V
1U
0T
0S
0R
0Q
1P
1O
0N
0M
0L
0K
1J
1I
0H
0G
0F
0E
1D
1C
0B
0A
0@
0?
1>
1=
0<
0;
1:
09
18
17
06
05
14
03
02
11
10
1/
1.
0-
1,
1+
0*
0)
1(
b1111010 '
b1111010 &
b110011000011 %
1$
b1111010 #
b110011000011 "
b1111010 !
$end
#1
1*
16
1<
1Z
1&"
0+
01
07
0=
0f
0l
b111000001111 !
b111000001111 '
0r
0[
0a
0'"
1-
12
13
19
1?
1E
1K
1Q
1W
1]
1b
1c
1h
1i
1n
1o
1t
1u
1{
1#"
1)"
1Y
0_
0q
1;
1X
1^
0p
0v
1$"
0$
b100000110110 #
b100000110110 &
b111000001111 "
b111000001111 %
#2
0*
00
1~
0&"
06
b1100100001100 !
b1100100001100 '
1B
1+
11
0!"
1'"
17
0C
0/
0Y
1_
0e
1q
15
1M
0(
0.
1|
0$"
04
1@
b100110001101000 #
b100110001101000 &
b1100100001100 "
b1100100001100 %
#3
1*
10
0Z
0`
1l
1r
0~
b1101001100011 !
b1101001100011 '
1&"
0+
01
1[
1a
0m
0s
1!"
0'"
1/
1Y
0_
1e
0k
1%"
1A
0M
1S
1(
1.
0X
0^
1j
1p
0|
1$"
b1001111001010110 #
b1001111001010110 &
b1101001100011 "
b1101001100011 %
#4
00
0<
0l
1+
11
1=
1C
1H
1Z
b11001001010101 !
b11001001010101 '
1f
1s
1'"
1m
0,
0-
03
09
0?
0D
0E
0J
0K
0Q
0W
0\
0]
0c
0h
0i
0o
0t
0u
0{
0#"
0("
0)"
1)
0/
05
0;
1G
0S
1X
1^
0j
1v
1|
14
1$
b11001001010101 #
b11001001010101 &
b1111111001111 "
b1111111001111 %
#5
10
0f
0r
1~
0&"
0B
b1010000100000111 !
b1010000100000111 '
1T
02
1h
1t
0""
1("
1D
0V
1/
0e
0q
1}
0%"
0A
1S
0.
0X
0p
0|
1F
b1010000100000111 #
b1010000100000111 &
b11111010001001 "
b11111010001001 %
#6
16
1B
1x
1N
0+
00
07
0C
0H
0T
0Z
0y
b101010010000001 !
b101010010000001 '
0~
0O
1,
1-
12
13
19
1?
1E
1J
1K
1Q
1V
1W
1\
1]
1c
1i
1o
1u
1{
1""
1#"
1)"
0)
0Y
1_
1e
1k
1q
1w
1;
0G
0S
0^
0$"
0:
0F
1L
0$
b100111111010 #
b100111111010 &
b101010010000001 "
b101010010000001 %
#7
1`
1f
0x
1~
1&"
06
b101101100011001 !
b101101100011001 '
1<
0a
0g
1y
0!"
0'"
17
0=
0w
15
0;
1A
1G
1M
1S
1^
1d
0v
1|
1$"
04
1:
b1111010101111010 #
b1111010101111010 &
b101101100011001 "
b101101100011001 %
#8
0<
0B
0N
0`
0f
0~
0&"
0*
10
16
1=
1C
1O
1T
b1000010000000110 !
b1000010000000110 '
1Z
1a
1g
1!"
1'"
1+
0-
02
03
08
09
0?
0E
0K
0Q
0V
0W
0\
0]
0c
0i
0o
0u
0{
0#"
0)"
1Y
0_
0e
0k
0q
0}
0A
0G
0M
0(
1j
1p
1$
b1000010000000110 #
b1000010000000110 &
b101101101111000 "
b101101101111000 %
#9
1*
0Z
1`
1r
1&"
b1000001001001011 !
b1000001001001011 '
06
0,
1\
0b
0t
0("
18
1)
0Y
1_
1q
1%"
05
1(
1X
0d
0$"
0:
0@
1F
b1000001001001011 #
b1000001001001011 &
b110000101101101 "
b110000101101101 %
#10
0*
1Z
0`
1f
16
1<
b111001010110 !
b111001010110 '
0T
1,
0\
1b
0h
08
0>
1V
0)
1Y
0_
1e
15
1;
0S
0(
1.
0X
0^
0j
0p
0|
1$"
1:
b111001010110 #
b111001010110 &
b110101000000010 "
b110101000000010 %
#11
1H
1N
1l
1~
01
0=
0I
0O
0Z
0f
b110110101100010 !
b110110101100010 '
0&"
0m
0s
0!"
07
1-
12
13
18
19
1>
1?
1E
1K
1Q
1W
1\
1]
1c
1h
1i
1o
1t
1u
1{
1#"
1("
1)"
1)
0/
0Y
1_
0e
0q
1w
0%"
05
0;
1G
1S
1j
1p
1|
0$"
14
0$
b1010000010001001 #
b1010000010001001 &
b110110101100010 "
b110110101100010 %
#12
0H
0N
11
1Z
b110101110110 !
b110101110110 '
1f
1m
1s
1!"
17
1=
1I
1O
0-
02
03
08
09
0>
0?
0E
0K
0Q
0W
0\
0]
0c
0h
0i
0n
0o
0t
0u
0{
0""
0#"
0)"
0)
1/
1Y
0_
1e
1k
1q
0w
1}
15
1;
0G
0S
1^
1d
0j
0p
0|
04
0:
0F
0L
1R
1$
b110101110110 #
b110101110110 &
b1000000000011010 "
b1000000000011010 %
#13
00
0Z
0l
0r
0~
1&"
1B
b1001111000010000 !
b1001111000010000 '
1T
12
1\
1n
1t
1""
0("
0D
0V
0/
0Y
0k
0q
0}
1%"
1A
1S
1(
0^
1p
1|
14
b1001111000010000 #
b1001111000010000 &
b1000010101010011 "
b1000010101010011 %
#14
1`
0f
1l
1x
06
0<
b1001010101000 !
b1001010101000 '
0T
0b
1h
0n
0z
18
1>
1V
1_
0e
1k
1w
05
0;
0S
0(
0.
1^
1v
0|
04
1@
b1001010101000 #
b1001010101000 &
b1001000011011000 "
b1001000011011000 %
#15
1*
10
1f
0&"
0B
1H
b110000010111011 !
b110000010111011 '
1N
0,
02
0h
1("
1D
0J
0P
1)
1/
1e
0%"
0A
1G
1M
0^
0d
0p
0v
1$"
14
b110000010111011 #
b110000010111011 &
b1001011000000000 "
b1001011000000000 %
#16
16
1B
1T
1&"
1r
1~
0*
07
0C
0H
0N
0U
0`
b1001011111100010 !
b1001011111100010 '
0f
0'"
01
0m
0s
0y
0!"
1,
1-
12
13
19
1?
1E
1J
1K
1P
1Q
1W
1]
1b
1c
1h
1i
1n
1o
1u
1z
1{
1#"
1)"
0)
0/
1Y
0_
1q
1}
1%"
15
1;
0G
1S
1.
1j
1p
1v
1|
0$
b1100111111110100 #
b1100111111110100 &
b1001011111100010 "
b1001011111100010 %
#17
0x
0r
0~
0&"
1<
1H
1U
1`
b1011110000111010 !
b1011110000111010 '
1f
1m
1y
11
1s
1!"
1'"
17
1C
0-
02
03
08
09
0>
0?
0D
0E
0J
0K
0Q
0V
0W
0]
0b
0c
0h
0i
0n
0o
0u
0{
0#"
0)"
1/
0Y
1_
0q
0w
0}
0%"
1A
1G
0M
1(
0.
1X
1d
0p
0|
0$"
04
0@
1F
1$
b1011110000111010 #
b1011110000111010 &
b1010000010110101 "
b1010000010110101 %
#18
1*
1x
1r
1~
1&"
0+
0<
0B
0I
0U
0`
0g
b1010011111010011 !
b1010011111010011 '
0l
0y
01
0s
0!"
0'"
07
1-
12
13
18
19
1>
1?
1D
1E
1J
1K
1Q
1V
1W
1]
1b
1c
1h
1i
1n
1o
1u
1{
1#"
1)"
1)
0_
0k
1q
1w
05
0;
1.
0X
0j
1p
1|
1$"
14
0$
b1011000011010011 #
b1011000011010011 &
b1010011111010011 "
b1010011111010011 %
#19
0&"
0r
0x
b1010010000010011 !
b1010010000010011 '
0~
1+
17
1I
1U
1g
1'"
11
1s
1y
1!"
0,
0-
02
03
08
09
0?
0E
0J
0K
0Q
0V
0W
0]
0c
0h
0i
0o
0u
0{
0#"
0)"
0q
0w
15
0A
0.
1X
1^
1j
0p
0v
0|
1:
1$
b1010010000010011 #
b1010010000010011 &
b1010111000111101 "
b1010111000111101 %
#20
0*
00
1`
0f
1l
1x
1~
1&"
b1010111110101000 !
b1010111110101000 '
1<
1,
12
0b
1h
0n
0z
0""
0("
0>
0)
0/
1_
0e
1k
1w
1}
1%"
1;
0(
1.
0X
0d
0j
1p
1v
04
0:
1@
b1010111110101000 #
b1010111110101000 &
b1011001011001010 "
b1011001011001010 %
#21
1*
10
0`
1f
1r
0~
0<
1B
0H
b1101011011110011 !
b1101011011110011 '
1N
0,
02
1b
0h
0t
1""
1>
0D
1J
0P
1)
1/
0_
1e
1q
0}
0;
1A
0G
1M
1X
1d
1j
0p
0$"
14
b1101011011110011 #
b1101011011110011 &
b1011010010111110 "
b1011010010111110 %
#22
00
0l
1~
06
b1111001111010001 !
b1111001111010001 '
1H
12
1n
0""
18
0J
0/
0k
1}
05
1G
1(
0X
1|
1$"
b1111001111010001 #
b1111001111010001 &
b1011011110111011 "
b1011011110111011 %
#23
10
16
1`
1l
1Z
1<
0*
01
07
0C
0I
0N
0U
0a
0g
0m
0r
0y
b1011111010111110 !
b1011111010111110 '
0~
0'"
0[
0=
1,
1-
13
19
1?
1D
1E
1J
1K
1P
1Q
1V
1W
1]
1c
1h
1i
1o
1t
1u
1z
1{
1""
1#"
1("
1)"
0)
1/
0e
0}
0%"
0G
0M
0(
1X
0|
1:
0$
b1001000011000010 #
b1001000011000010 &
b1011111010111110 "
b1011111010111110 %
#24
0f
0&"
0<
0B
0H
b1100010010101110 !
b1100010010101110 '
1N
1g
1'"
1=
1C
1I
0O
1k
0w
1%"
15
1G
1M
0S
0d
0$"
0:
0@
0F
1L
b111011001100010 #
b111011001100010 &
b1100010010101110 "
b1100010010101110 %
#25
0Z
1r
1&"
06
1<
b1101101011101010 !
b1101101011101010 '
1B
1[
0s
0'"
17
0=
0C
1_
0k
1;
0A
0G
0M
1S
0X
1p
1$"
04
1:
1@
b1000111001001010 #
b1000111001001010 &
b1101101011101010 "
b1101101011101010 %
#26
0<
0N
0T
0&"
00
0`
16
1=
1C
b11010011100000 !
b11010011100000 '
1H
1O
1U
1m
1y
1'"
11
1a
1s
0-
03
08
09
0?
0D
0E
0J
0K
0Q
0W
0]
0c
0i
0n
0o
0t
0u
0z
0{
0#"
0)"
0/
0_
1k
1w
0%"
0;
1A
1G
0S
1(
0.
1X
0^
1d
0p
1|
1$
b11010011100000 #
b11010011100000 &
b1101101110110101 "
b1101101110110101 %
#27
1*
10
1Z
1`
0l
0r
0x
1&"
06
0B
b110001000001111 !
b110001000001111 '
1N
0,
02
0\
0b
1n
1t
1z
0("
18
1D
0P
1)
1/
1Y
1_
0k
0q
0w
1%"
05
0A
1M
1.
0X
0d
0v
0|
0$"
14
b110001000001111 #
b110001000001111 &
b1101110000100011 "
b1101110000100011 %
#28
1<
1T
1r
1x
1~
0+
01
0=
0O
0U
b1110100111001111 !
b1110100111001111 '
0&"
0[
0a
0s
0y
0!"
0I
1,
1-
12
13
19
1?
1E
1J
1K
1P
1Q
1W
1\
1]
1b
1c
1i
1o
1u
1{
1#"
1("
1)"
0)
0_
1e
1k
1}
0M
1S
1X
1^
0j
1p
1v
1|
04
0@
1F
0$
b1010001100110110 #
b1010001100110110 &
b1110100111001111 "
b1110100111001111 %
#29
0*
1f
0~
0<
b1111000011011110 !
b1111000011011110 '
1B
1+
0g
1!"
1=
0C
0Y
1_
0k
1;
0G
1M
0S
0(
1d
0|
0:
1@
b100101100011010 #
b100101100011010 &
b1111000011011110 "
b1111000011011110 %
