Elementos de Sistemas Computacionais/Mux.v
/* módulo Mux */

`ifndef _Mux_
`define _Mux_

module Mux(out, a, b, sel);
    input a, b, sel;
    output out;
    wire w0, w1, w2;

    
    nand nand0(w0, a, w2);
    nand nand1(w1, b, sel);
    nand nand2(out, w0, w1);
    not not0(w2, sel);

    // Descrição de conexões internas do módulo

endmodule

`endif

Elementos de Sistemas Computacionais/Mux4Way.v
/* módulo Mux4Way */

`ifndef _Mux4Way_
`define _Mux4Way_

`include "Mux.v"

module Mux4Way(out, a, b, c, d, sel);
    input a, b, c, d;
    input [1:0] sel;
    output out;
    wire w0, w1;

    //

    Mux mux0(w0, a, b, sel[0]);
    Mux mux1(w1, c, d, sel[0]);
    Mux mux2(out, w0, w1, sel[1]);



endmodule

`endif

Elementos de Sistemas Computacionais/tb_Mux4Way.v
/* testbench para Mux4Way */
/* ordem de portas: out, a, b, c, d, sel */
/* input a; input b; input c; input d; input [1:0] sel; */
/* output out; */

`include "Mux4Way.v"

`define assert(signal, value) \
    if (signal !== value) \
    begin \
        $display("ASSERTION FAILED in %m: signal != value"); \
        $finish; \
    end else begin \
        $display("Success! %m: signal = value"); \
    end

module tb_Mux4Way;
    reg a;
    reg b;
    reg c;
    reg d;
    reg [1:0] sel;
    wire out;

    Mux4Way mymodule(out, a, b, c, d, sel);
    
    initial
    begin
        $dumpfile("tb_Mux4Way.vcd");
        $dumpvars(0, tb_Mux4Way);

        a = 1'b0; b = 1'b0; c = 1'b0; d = 1'b0; sel = 2'b00; #1;
         `assert(out, 1'b0)
        a = 1'b0; b = 1'b0; c = 1'b0; d = 1'b0; sel = 2'b00; #1;
         `assert(out, 1'b0)
        a = 1'b0; b = 1'b0; c = 1'b0; d = 1'b1; sel = 2'b00; #1;
         `assert(out, 1'b0)
        a = 1'b0; b = 1'b0; c = 1'b0; d = 1'b1; sel = 2'b00; #1;
         `assert(out, 1'b0)
        a = 1'b0; b = 1'b0; c = 1'b0; d = 1'b1; sel = 2'b01; #1;
         `assert(out, 1'b0)
        a = 1'b0; b = 1'b0; c = 1'b0; d = 1'b1; sel = 2'b10; #1;
         `assert(out, 1'b0)
        a = 1'b0; b = 1'b0; c = 1'b1; d = 1'b0; sel = 2'b00; #1;
         `assert(out, 1'b0)
        a = 1'b0; b = 1'b0; c = 1'b1; d = 1'b0; sel = 2'b01; #1;
         `assert(out, 1'b0)
        a = 1'b0; b = 1'b0; c = 1'b1; d = 1'b0; sel = 2'b11; #1;
         `assert(out, 1'b0)
        a = 1'b0; b = 1'b1; c = 1'b0; d = 1'b1; sel = 2'b00; #1;
         `assert(out, 1'b0)
        a = 1'b0; b = 1'b1; c = 1'b0; d = 1'b1; sel = 2'b00; #1;
         `assert(out, 1'b0)
        a = 1'b0; b = 1'b1; c = 1'b0; d = 1'b1; sel = 2'b00; #1;
         `assert(out, 1'b0)
        a = 1'b0; b = 1'b1; c = 1'b1; d = 1'b0; sel = 2'b10; #1;
         `assert(out, 1'b1)
        a = 1'b0; b = 1'b1; c = 1'b1; d = 1'b0; sel = 2'b11; #1;
         `assert(out, 1'b0)
        a = 1'b1; b = 1'b0; c = 1'b0; d = 1'b0; sel = 2'b01; #1;
         `assert(out, 1'b0)
        a = 1'b1; b = 1'b0; c = 1'b0; d = 1'b0; sel = 2'b01; #1;
         `assert(out, 1'b0)
        a = 1'b1; b = 1'b0; c = 1'b0; d = 1'b0; sel = 2'b01; #1;
         `assert(out, 1'b0)
        a = 1'b1; b = 1'b0; c = 1'b0; d = 1'b0; sel = 2'b10; #1;
         `assert(out, 1'b0)
        a = 1'b1; b = 1'b0; c = 1'b0; d = 1'b1; sel = 2'b01; #1;
         `assert(out, 1'b0)
        a = 1'b1; b = 1'b0; c = 1'b0; d = 1'b1; sel = 2'b10; #1;
         `assert(out, 1'b0)
        a = 1'b1; b = 1'b0; c = 1'b0; d = 1'b1; sel = 2'b11; #1;
         `assert(out, 1'b1)
        a = 1'b1; b = 1'b0; c = 1'b1; d = 1'b0; sel = 2'b00; #1;
         `assert(out, 1'b1)
        a = 1'b1; b = 1'b0; c = 1'b1; d = 1'b0; sel = 2'b10; #1;
         `assert(out, 1'b1)
        a = 1'b1; b = 1'b1; c = 1'b0; d = 1'b0; sel = 2'b10; #1;
         `assert(out, 1'b0)
        a = 1'b1; b = 1'b1; c = 1'b0; d = 1'b0; sel = 2'b10; #1;
         `assert(out, 1'b0)
        a = 1'b1; b = 1'b1; c = 1'b1; d = 1'b1; sel = 2'b01; #1;
         `assert(out, 1'b1)
        a = 1'b1; b = 1'b1; c = 1'b1; d = 1'b1; sel = 2'b10; #1;
         `assert(out, 1'b1)
        a = 1'b1; b = 1'b1; c = 1'b1; d = 1'b1; sel = 2'b10; #1;
         `assert(out, 1'b1)
        a = 1'b1; b = 1'b1; c = 1'b1; d = 1'b1; sel = 2'b10; #1;
         `assert(out, 1'b1)
        a = 1'b1; b = 1'b1; c = 1'b1; d = 1'b1; sel = 2'b11; #1;
         `assert(out, 1'b1)

    end
endmodule

Elementos de Sistemas Computacionais/tb_Mux4Way.vcd
$date
	Sun Apr 23 11:22:27 2023
$end
$version
	Icarus Verilog
$end
$timescale
	1s
$end
$scope module tb_Mux4Way $end
$var wire 1 ! out $end
$var reg 1 " a $end
$var reg 1 # b $end
$var reg 1 $ c $end
$var reg 1 % d $end
$var reg 2 & sel [1:0] $end
$scope module mymodule $end
$var wire 1 " a $end
$var wire 1 # b $end
$var wire 1 $ c $end
$var wire 1 % d $end
$var wire 2 ' sel [1:0] $end
$var wire 1 ( w1 $end
$var wire 1 ) w0 $end
$var wire 1 ! out $end
$scope module mux0 $end
$var wire 1 " a $end
$var wire 1 # b $end
$var wire 1 ) out $end
$var wire 1 * sel $end
$var wire 1 + w0 $end
$var wire 1 , w1 $end
$var wire 1 - w2 $end
$upscope $end
$scope module mux1 $end
$var wire 1 $ a $end
$var wire 1 % b $end
$var wire 1 ( out $end
$var wire 1 . sel $end
$var wire 1 / w0 $end
$var wire 1 0 w1 $end
$var wire 1 1 w2 $end
$upscope $end
$scope module mux2 $end
$var wire 1 ) a $end
$var wire 1 ( b $end
$var wire 1 ! out $end
$var wire 1 2 sel $end
$var wire 1 3 w0 $end
$var wire 1 4 w1 $end
$var wire 1 5 w2 $end
$upscope $end
$upscope $end
$upscope $end
$enddefinitions $end
$comment Show the parameter values. $end
$dumpall
$end
#0
$dumpvars
15
14
13
02
11
10
1/
0.
1-
1,
1+
0*
0)
0(
b0 '
b0 &
0%
0$
0#
0"
0!
$end
#2
1%
#4
1(
0-
00
01
1*
1.
b1 &
b1 '
#5
0(
0!
1-
10
11
14
05
0*
0.
12
b10 &
b10 '
#6
15
1(
02
0/
b0 &
b0 '
0%
1$
#7
0(
1/
0-
01
1*
1.
b1 &
b1 '
#8
05
12
b11 &
b11 '
#9
0!
13
1-
11
15
0(
0)
0*
0.
02
10
1,
b0 &
b0 '
1%
0$
1#
#12
1!
04
05
1(
12
0/
b10 &
b10 '
0%
1$
#13
0!
14
0(
1)
1/
0,
0-
01
1*
1.
b11 &
b11 '
#14
15
0)
02
1,
b1 &
b1 '
0$
0#
1"
#17
1)
0+
1-
11
05
0*
0.
12
b10 &
b10 '
#18
0)
0!
1+
1(
13
0-
00
01
15
1*
1.
02
b1 &
b1 '
1%
#19
1)
0+
0(
0!
1-
10
11
14
05
0*
0.
12
b10 &
b10 '
#20
1!
0)
04
1+
1(
0-
00
01
1*
1.
b11 &
b11 '
#21
03
1)
0+
0/
1!
1-
11
14
15
1(
0*
0.
02
10
b0 &
b0 '
0%
1$
#22
13
04
05
12
b10 &
b10 '
#23
0!
14
0(
1/
0$
1#
#25
1!
1+
03
0,
0-
00
01
15
1(
1*
1.
02
1/
b1 &
b1 '
1%
1$
#26
0+
0/
13
1,
1-
10
11
04
05
0*
0.
12
b10 &
b10 '
#29
1+
1/
0,
0-
00
01
1*
1.
b11 &
b11 '
