Elementos de Sistemas Computacionais/Not16.v
/* módulo Not16 */

`ifndef _Not16_
`define _Not16_

module Not16(out, in);
    input [15:0] in;
    output [15:0] out ;

    not not0(out[0], in[0]);
    not not1(out[1], in[1]);
    not not2(out[2], in[2]);
    not not3(out[3], in[3]);
    not not4(out[4], in[4]);
    not not5(out[5], in[5]);
    not not6(out[6], in[6]);
    not not7(out[7], in[7]);
    not not8(out[8], in[8]);
    not not9(out[9], in[9]);
    not not10(out[10], in[10]);
    not not11(out[11], in[11]);
    not not12(out[12], in[12]);
    not not13(out[13], in[13]);
    not not14(out[14], in[14]);
    not not15(out[15], in[15]);

    // Descrição de conexões internas do módulo

endmodule

`endif

Elementos de Sistemas Computacionais/tb_Not16.v
/* testbench para Not16 */
/* ordem de portas: out, in */
/* input [15:0] in; */
/* output [15:0] out; */

`include "Not16.v"

`define assert(signal, value) \
    if (signal !== value) \
    begin \
        $display("ASSERTION FAILED in %m: signal != value"); \
        $finish; \
    end else begin \
        $display("Success! %m: signal = value"); \
    end

module tb_Not16;
    reg [15:0] in;
    wire [15:0] out;

    Not16 mymodule(out, in);
    
    initial
    begin
        $dumpfile("tb_Not16.vcd");
        $dumpvars(0, tb_Not16);

        in = 16'b0000011011101110; #1;
         `assert(out, 16'b1111100100010001)
        in = 16'b0000111011100110; #1;
         `assert(out, 16'b1111000100011001)
        in = 16'b0000111110110100; #1;
         `assert(out, 16'b1111000001001011)
        in = 16'b0010001001101100; #1;
         `assert(out, 16'b1101110110010011)
        in = 16'b0011011101111010; #1;
         `assert(out, 16'b1100100010000101)
        in = 16'b0011100000010110; #1;
         `assert(out, 16'b1100011111101001)
        in = 16'b0011100010111101; #1;
         `assert(out, 16'b1100011101000010)
        in = 16'b0011100101111001; #1;
         `assert(out, 16'b1100011010000110)
        in = 16'b0100100000000111; #1;
         `assert(out, 16'b1011011111111000)
        in = 16'b0110001000111001; #1;
         `assert(out, 16'b1001110111000110)
        in = 16'b0111010110100111; #1;
         `assert(out, 16'b1000101001011000)
        in = 16'b0111011000001010; #1;
         `assert(out, 16'b1000100111110101)
        in = 16'b0111110010111011; #1;
         `assert(out, 16'b1000001101000100)
        in = 16'b1000000111010000; #1;
         `assert(out, 16'b0111111000101111)
        in = 16'b1000010111110010; #1;
         `assert(out, 16'b0111101000001101)
        in = 16'b1000110011001011; #1;
         `assert(out, 16'b0111001100110100)
        in = 16'b1000111011000101; #1;
         `assert(out, 16'b0111000100111010)
        in = 16'b1001100000111100; #1;
         `assert(out, 16'b0110011111000011)
        in = 16'b1001100011000111; #1;
         `assert(out, 16'b0110011100111000)
        in = 16'b1001110011011101; #1;
         `assert(out, 16'b0110001100100010)
        in = 16'b1010011011001010; #1;
         `assert(out, 16'b0101100100110101)
        in = 16'b1100000101101111; #1;
         `assert(out, 16'b0011111010010000)
        in = 16'b1100100010100101; #1;
         `assert(out, 16'b0011011101011010)
        in = 16'b1100101101111110; #1;
         `assert(out, 16'b0011010010000001)
        in = 16'b1101110111010100; #1;
         `assert(out, 16'b0010001000101011)
        in = 16'b1101111010000000; #1;
         `assert(out, 16'b0010000101111111)
        in = 16'b1110111010100000; #1;
         `assert(out, 16'b0001000101011111)
        in = 16'b1111001011110100; #1;
         `assert(out, 16'b0000110100001011)
        in = 16'b1111101010000011; #1;
         `assert(out, 16'b0000010101111100)
        in = 16'b1111110010010000; #1;
         `assert(out, 16'b0000001101101111)

    end
endmodule

Elementos de Sistemas Computacionais/tb_Not16.vcd
$date
	Sun Apr 23 11:46:45 2023
$end
$version
	Icarus Verilog
$end
$timescale
	1s
$end
$scope module tb_Not16 $end
$var wire 16 ! out [15:0] $end
$var reg 16 " in [15:0] $end
$scope module mymodule $end
$var wire 16 # in [15:0] $end
$var wire 16 $ out [15:0] $end
$upscope $end
$upscope $end
$enddefinitions $end
$comment Show the parameter values. $end
$dumpall
$end
#0
$dumpvars
b1111100100010001 $
b11011101110 #
b11011101110 "
b1111100100010001 !
$end
#1
b1111000100011001 !
b1111000100011001 $
b111011100110 "
b111011100110 #
#2
b1111000001001011 !
b1111000001001011 $
b111110110100 "
b111110110100 #
#3
b1101110110010011 !
b1101110110010011 $
b10001001101100 "
b10001001101100 #
#4
b1100100010000101 !
b1100100010000101 $
b11011101111010 "
b11011101111010 #
#5
b1100011111101001 !
b1100011111101001 $
b11100000010110 "
b11100000010110 #
#6
b1100011101000010 !
b1100011101000010 $
b11100010111101 "
b11100010111101 #
#7
b1100011010000110 !
b1100011010000110 $
b11100101111001 "
b11100101111001 #
#8
b1011011111111000 !
b1011011111111000 $
b100100000000111 "
b100100000000111 #
#9
b1001110111000110 !
b1001110111000110 $
b110001000111001 "
b110001000111001 #
#10
b1000101001011000 !
b1000101001011000 $
b111010110100111 "
b111010110100111 #
#11
b1000100111110101 !
b1000100111110101 $
b111011000001010 "
b111011000001010 #
#12
b1000001101000100 !
b1000001101000100 $
b111110010111011 "
b111110010111011 #
#13
b111111000101111 !
b111111000101111 $
b1000000111010000 "
b1000000111010000 #
#14
b111101000001101 !
b111101000001101 $
b1000010111110010 "
b1000010111110010 #
#15
b111001100110100 !
b111001100110100 $
b1000110011001011 "
b1000110011001011 #
#16
b111000100111010 !
b111000100111010 $
b1000111011000101 "
b1000111011000101 #
#17
b110011111000011 !
b110011111000011 $
b1001100000111100 "
b1001100000111100 #
#18
b110011100111000 !
b110011100111000 $
b1001100011000111 "
b1001100011000111 #
#19
b110001100100010 !
b110001100100010 $
b1001110011011101 "
b1001110011011101 #
#20
b101100100110101 !
b101100100110101 $
b1010011011001010 "
b1010011011001010 #
#21
b11111010010000 !
b11111010010000 $
b1100000101101111 "
b1100000101101111 #
#22
b11011101011010 !
b11011101011010 $
b1100100010100101 "
b1100100010100101 #
#23
b11010010000001 !
b11010010000001 $
b1100101101111110 "
b1100101101111110 #
#24
b10001000101011 !
b10001000101011 $
b1101110111010100 "
b1101110111010100 #
#25
b10000101111111 !
b10000101111111 $
b1101111010000000 "
b1101111010000000 #
#26
b1000101011111 !
b1000101011111 $
b1110111010100000 "
b1110111010100000 #
#27
b110100001011 !
b110100001011 $
b1111001011110100 "
b1111001011110100 #
#28
b10101111100 !
b10101111100 $
b1111101010000011 "
b1111101010000011 #
#29
b1101101111 !
b1101101111 $
b1111110010010000 "
b1111110010010000 #
