Elementos de Sistemas Computacionais/Or8Way.v
/* módulo Or8Way */

`ifndef _Or8Way_
`define _Or8Way_

module Or8Way(out, a, b, c, d, e, f, g, h);
    input a, b, c, d, e, f, g, h;
    output out;
    wire w0, w1, w2, w3, w4, w5;

    or or0(w0, a, b);
    or or1(w1, c, d);
    or or2(w2, e, f);
    or or3(w3, g, h);
    or or4(w4, w0, w1);
    or or5(w5, w2, w3);
    or or6(out, w5, w4);

endmodule

`endif

Elementos de Sistemas Computacionais/tb_Or8Way.v
/* testbench para Or8Way */
/* ordem de portas: out, a, b, c, d, e, f, g, h */
/* input a; input b; input c; input d; input e; input f; input g; input h; */
/* output out; */

`include "Or8Way.v"

`define assert(signal, value) \
    if (signal !== value) \
    begin \
        $display("ASSERTION FAILED in %m: signal != value"); \
        $finish; \
    end else begin \
        $display("Success! %m: signal = value"); \
    end

module tb_Or8Way;
    reg a;
    reg b;
    reg c;
    reg d;
    reg e;
    reg f;
    reg g;
    reg h;
    wire out;

    Or8Way mymodule(out, a, b, c, d, e, f, g, h);
    
    initial
    begin
        $dumpfile("tb_Or8Way.vcd");
        $dumpvars(0, tb_Or8Way);

        a = 1'b0; b = 1'b0; c = 1'b0; d = 1'b0; e = 1'b0; f = 1'b0; g = 1'b0; h = 1'b0; #1;
         `assert(out, 1'b0)
        a = 1'b0; b = 1'b0; c = 1'b0; d = 1'b0; e = 1'b0; f = 1'b0; g = 1'b1; h = 1'b0; #1;
         `assert(out, 1'b1)
        a = 1'b0; b = 1'b0; c = 1'b0; d = 1'b0; e = 1'b0; f = 1'b1; g = 1'b0; h = 1'b1; #1;
         `assert(out, 1'b1)
        a = 1'b0; b = 1'b0; c = 1'b0; d = 1'b0; e = 1'b1; f = 1'b1; g = 1'b0; h = 1'b0; #1;
         `assert(out, 1'b1)
        a = 1'b0; b = 1'b0; c = 1'b0; d = 1'b1; e = 1'b1; f = 1'b1; g = 1'b0; h = 1'b0; #1;
         `assert(out, 1'b1)
        a = 1'b0; b = 1'b0; c = 1'b1; d = 1'b0; e = 1'b0; f = 1'b0; g = 1'b0; h = 1'b1; #1;
         `assert(out, 1'b1)
        a = 1'b0; b = 1'b0; c = 1'b1; d = 1'b0; e = 1'b0; f = 1'b0; g = 1'b1; h = 1'b0; #1;
         `assert(out, 1'b1)
        a = 1'b0; b = 1'b0; c = 1'b1; d = 1'b0; e = 1'b0; f = 1'b1; g = 1'b1; h = 1'b0; #1;
         `assert(out, 1'b1)
        a = 1'b0; b = 1'b0; c = 1'b1; d = 1'b0; e = 1'b1; f = 1'b1; g = 1'b1; h = 1'b1; #1;
         `assert(out, 1'b1)
        a = 1'b0; b = 1'b1; c = 1'b0; d = 1'b0; e = 1'b1; f = 1'b0; g = 1'b0; h = 1'b0; #1;
         `assert(out, 1'b1)
        a = 1'b0; b = 1'b1; c = 1'b0; d = 1'b0; e = 1'b1; f = 1'b1; g = 1'b1; h = 1'b0; #1;
         `assert(out, 1'b1)
        a = 1'b0; b = 1'b1; c = 1'b0; d = 1'b1; e = 1'b0; f = 1'b1; g = 1'b0; h = 1'b1; #1;
         `assert(out, 1'b1)
        a = 1'b0; b = 1'b1; c = 1'b1; d = 1'b0; e = 1'b1; f = 1'b1; g = 1'b0; h = 1'b1; #1;
         `assert(out, 1'b1)
        a = 1'b0; b = 1'b1; c = 1'b1; d = 1'b1; e = 1'b0; f = 1'b0; g = 1'b0; h = 1'b1; #1;
         `assert(out, 1'b1)
        a = 1'b0; b = 1'b1; c = 1'b1; d = 1'b1; e = 1'b0; f = 1'b1; g = 1'b0; h = 1'b1; #1;
         `assert(out, 1'b1)
        a = 1'b0; b = 1'b1; c = 1'b1; d = 1'b1; e = 1'b1; f = 1'b0; g = 1'b0; h = 1'b0; #1;
         `assert(out, 1'b1)
        a = 1'b0; b = 1'b1; c = 1'b1; d = 1'b1; e = 1'b1; f = 1'b0; g = 1'b1; h = 1'b0; #1;
         `assert(out, 1'b1)
        a = 1'b1; b = 1'b0; c = 1'b0; d = 1'b1; e = 1'b0; f = 1'b0; g = 1'b1; h = 1'b1; #1;
         `assert(out, 1'b1)
        a = 1'b1; b = 1'b0; c = 1'b0; d = 1'b1; e = 1'b1; f = 1'b1; g = 1'b1; h = 1'b1; #1;
         `assert(out, 1'b1)
        a = 1'b1; b = 1'b0; c = 1'b1; d = 1'b0; e = 1'b1; f = 1'b0; g = 1'b1; h = 1'b0; #1;
         `assert(out, 1'b1)
        a = 1'b1; b = 1'b0; c = 1'b1; d = 1'b1; e = 1'b0; f = 1'b1; g = 1'b0; h = 1'b1; #1;
         `assert(out, 1'b1)
        a = 1'b1; b = 1'b0; c = 1'b1; d = 1'b1; e = 1'b0; f = 1'b1; g = 1'b0; h = 1'b1; #1;
         `assert(out, 1'b1)
        a = 1'b1; b = 1'b1; c = 1'b0; d = 1'b0; e = 1'b0; f = 1'b0; g = 1'b0; h = 1'b0; #1;
         `assert(out, 1'b1)
        a = 1'b1; b = 1'b1; c = 1'b0; d = 1'b0; e = 1'b1; f = 1'b0; g = 1'b0; h = 1'b1; #1;
         `assert(out, 1'b1)
        a = 1'b1; b = 1'b1; c = 1'b0; d = 1'b1; e = 1'b1; f = 1'b0; g = 1'b0; h = 1'b0; #1;
         `assert(out, 1'b1)
        a = 1'b1; b = 1'b1; c = 1'b0; d = 1'b1; e = 1'b1; f = 1'b1; g = 1'b0; h = 1'b0; #1;
         `assert(out, 1'b1)
        a = 1'b1; b = 1'b1; c = 1'b1; d = 1'b0; e = 1'b0; f = 1'b1; g = 1'b1; h = 1'b1; #1;
         `assert(out, 1'b1)
        a = 1'b1; b = 1'b1; c = 1'b1; d = 1'b0; e = 1'b1; f = 1'b0; g = 1'b1; h = 1'b0; #1;
         `assert(out, 1'b1)
        a = 1'b1; b = 1'b1; c = 1'b1; d = 1'b1; e = 1'b1; f = 1'b0; g = 1'b1; h = 1'b1; #1;
         `assert(out, 1'b1)
        a = 1'b1; b = 1'b1; c = 1'b1; d = 1'b1; e = 1'b1; f = 1'b1; g = 1'b1; h = 1'b1; #1;
         `assert(out, 1'b1)

    end
endmodule

Elementos de Sistemas Computacionais/tb_Or8Way.vcd
$date
	Sun Apr 23 12:14:10 2023
$end
$version
	Icarus Verilog
$end
$timescale
	1s
$end
$scope module tb_Or8Way $end
$var wire 1 ! out $end
$var reg 1 " a $end
$var reg 1 # b $end
$var reg 1 $ c $end
$var reg 1 % d $end
$var reg 1 & e $end
$var reg 1 ' f $end
$var reg 1 ( g $end
$var reg 1 ) h $end
$scope module mymodule $end
$var wire 1 " a $end
$var wire 1 # b $end
$var wire 1 $ c $end
$var wire 1 % d $end
$var wire 1 & e $end
$var wire 1 ' f $end
$var wire 1 ( g $end
$var wire 1 ) h $end
$var wire 1 ! out $end
$var wire 1 * w0 $end
$var wire 1 + w1 $end
$var wire 1 , w2 $end
$var wire 1 - w3 $end
$var wire 1 . w4 $end
$var wire 1 / w5 $end
$upscope $end
$upscope $end
$enddefinitions $end
$comment Show the parameter values. $end
$dumpall
$end
#0
$dumpvars
0/
0.
0-
0,
0+
0*
0)
0(
0'
0&
0%
0$
0#
0"
0!
$end
#1
1!
1/
1-
1(
#2
1,
1)
0(
1'
#3
0-
0)
1&
#4
1.
1+
1%
#5
1-
0,
1)
0'
0&
0%
1$
#6
0)
1(
#7
1,
1'
#8
1)
1&
#9
0-
0+
1*
0)
0(
0'
0$
1#
#10
1-
1(
1'
#11
1+
1)
0(
0&
1%
#12
1&
0%
1$
#13
0,
0'
0&
1%
#14
1,
1'
#15
0-
0)
0'
1&
#16
1-
1(
#17
0,
1)
0&
0$
0#
1"
#18
1,
1'
1&
#19
0)
0'
0%
1$
#20
1)
0(
1'
0&
1%
#22
0/
0-
0,
0+
0)
0'
0%
0$
1#
#23
1/
1-
1,
1)
1&
#24
0-
1+
0)
1%
#25
1'
#26
1-
1)
1(
0&
0%
1$
#27
0)
0'
1&
#28
1)
1%
#29
1'
