Elementos de Sistemas Computacionais/Tarefa01_12011ECP008GabrielAlves/Or16.v
/* módulo Or16 */

`ifndef _Or16_
`define _Or16_

module Or16(out, a, b);
    input [15:0] a, b;
    output [15:0] out ;

    or or0(out[0], a[0], b[0]);
    or or1(out[1], a[1], b[1]);
    or or2(out[2], a[2], b[2]);
    or or3(out[3], a[3], b[3]);
    or or4(out[4], a[4], b[4]);
    or or5(out[5], a[5], b[5]);
    or or6(out[6], a[6], b[6]);
    or or7(out[7], a[7], b[7]);
    or or8(out[8], a[8], b[8]);
    or or9(out[9], a[9], b[9]);
    or or10(out[10], a[10], b[10]);
    or or11(out[11], a[11], b[11]);
    or or12(out[12], a[12], b[12]);
    or or13(out[13], a[13], b[13]);
    or or14(out[14], a[14], b[14]);
    or or15(out[15], a[15], b[15]);

    // Descrição de conexões internas do módulo

endmodule

`endif

Elementos de Sistemas Computacionais/tb_Or16.v
/* testbench para Or16 */
/* ordem de portas: out, a, b */
/* input [15:0] a; input [15:0] b; */
/* output [15:0] out; */

`include "Or16.v"

`define assert(signal, value) \
    if (signal !== value) \
    begin \
        $display("ASSERTION FAILED in %m: signal != value"); \
        $finish; \
    end else begin \
        $display("Success! %m: signal = value"); \
    end

module tb_Or16;
    reg [15:0] a;
    reg [15:0] b;
    wire [15:0] out;

    Or16 mymodule(out, a, b);
    
    initial
    begin
        $dumpfile("tb_Or16.vcd");
        $dumpvars(0, tb_Or16);

        a = 16'b0000010001101010; b = 16'b1101111001010111; #1;
         `assert(out, 16'b1101111001111111)
        a = 16'b0000011111011000; b = 16'b0001000110011000; #1;
         `assert(out, 16'b0001011111011000)
        a = 16'b0001000011000000; b = 16'b1101011101101011; #1;
         `assert(out, 16'b1101011111101011)
        a = 16'b0001011010000101; b = 16'b0000110101000001; #1;
         `assert(out, 16'b0001111111000101)
        a = 16'b0001110111001011; b = 16'b1101101001100110; #1;
         `assert(out, 16'b1101111111101111)
        a = 16'b0010001011010110; b = 16'b0000101101001011; #1;
         `assert(out, 16'b0010101111011111)
        a = 16'b0010010101100010; b = 16'b0011100101011100; #1;
         `assert(out, 16'b0011110101111110)
        a = 16'b0010110100111001; b = 16'b1001100001111001; #1;
         `assert(out, 16'b1011110101111001)
        a = 16'b0010111100101110; b = 16'b1111011011011000; #1;
         `assert(out, 16'b1111111111111110)
        a = 16'b0011000100101110; b = 16'b0101001011101100; #1;
         `assert(out, 16'b0111001111101110)
        a = 16'b0011001010111100; b = 16'b0010001101100111; #1;
         `assert(out, 16'b0011001111111111)
        a = 16'b0011001101110010; b = 16'b1110000110100110; #1;
         `assert(out, 16'b1111001111110110)
        a = 16'b0100101100010001; b = 16'b1111111010001110; #1;
         `assert(out, 16'b1111111110011111)
        a = 16'b0101001000011011; b = 16'b0010001011011011; #1;
         `assert(out, 16'b0111001011011011)
        a = 16'b0101001101010100; b = 16'b1000100001010010; #1;
         `assert(out, 16'b1101101101010110)
        a = 16'b0101011101101011; b = 16'b0100000100110111; #1;
         `assert(out, 16'b0101011101111111)
        a = 16'b0111010100111111; b = 16'b1000010010100101; #1;
         `assert(out, 16'b1111010110111111)
        a = 16'b0111101111110110; b = 16'b1011111101010000; #1;
         `assert(out, 16'b1111111111110110)
        a = 16'b0111110111101111; b = 16'b1010110000001110; #1;
         `assert(out, 16'b1111110111101111)
        a = 16'b1000011111011101; b = 16'b0001111101101011; #1;
         `assert(out, 16'b1001111111111111)
        a = 16'b1000110000010011; b = 16'b0100101111100001; #1;
         `assert(out, 16'b1100111111110011)
        a = 16'b1000110101011001; b = 16'b0011001000010011; #1;
         `assert(out, 16'b1011111101011011)
        a = 16'b1001011001001000; b = 16'b0111110101101110; #1;
         `assert(out, 16'b1111111101101110)
        a = 16'b1001101011110111; b = 16'b1000100111101100; #1;
         `assert(out, 16'b1001101111111111)
        a = 16'b1010101000000010; b = 16'b0111001011000110; #1;
         `assert(out, 16'b1111101011000110)
        a = 16'b1011001100111001; b = 16'b0111001001011111; #1;
         `assert(out, 16'b1111001101111111)
        a = 16'b1011101011000001; b = 16'b1110001000010101; #1;
         `assert(out, 16'b1111101011010101)
        a = 16'b1100110111011000; b = 16'b0001000101101000; #1;
         `assert(out, 16'b1101110111111000)
        a = 16'b1100111001100101; b = 16'b1010010100110110; #1;
         `assert(out, 16'b1110111101110111)
        a = 16'b1111000111011001; b = 16'b1011000111000101; #1;
         `assert(out, 16'b1111000111011101)

    end
endmodule

Elementos de Sistemas Computacionais/tb_Or16.vcd
$date
	Thu Apr 20 09:43:19 2023
$end
$version
	Icarus Verilog
$end
$timescale
	1s
$end
$scope module tb_Or16 $end
$var wire 16 ! out [15:0] $end
$var reg 16 " a [15:0] $end
$var reg 16 # b [15:0] $end
$scope module mymodule $end
$var wire 16 $ a [15:0] $end
$var wire 16 % b [15:0] $end
$var wire 16 & out [15:0] $end
$upscope $end
$upscope $end
$enddefinitions $end
$comment Show the parameter values. $end
$dumpall
$end
#0
$dumpvars
b1101111001111111 &
b1101111001010111 %
b10001101010 $
b1101111001010111 #
b10001101010 "
b1101111001111111 !
$end
#1
b1011111011000 !
b1011111011000 &
b1000110011000 #
b1000110011000 %
b11111011000 "
b11111011000 $
#2
b1101011111101011 !
b1101011111101011 &
b1101011101101011 #
b1101011101101011 %
b1000011000000 "
b1000011000000 $
#3
b1111111000101 !
b1111111000101 &
b110101000001 #
b110101000001 %
b1011010000101 "
b1011010000101 $
#4
b1101111111101111 !
b1101111111101111 &
b1101101001100110 #
b1101101001100110 %
b1110111001011 "
b1110111001011 $
#5
b10101111011111 !
b10101111011111 &
b101101001011 #
b101101001011 %
b10001011010110 "
b10001011010110 $
#6
b11110101111110 !
b11110101111110 &
b11100101011100 #
b11100101011100 %
b10010101100010 "
b10010101100010 $
#7
b1011110101111001 !
b1011110101111001 &
b1001100001111001 #
b1001100001111001 %
b10110100111001 "
b10110100111001 $
#8
b1111111111111110 !
b1111111111111110 &
b1111011011011000 #
b1111011011011000 %
b10111100101110 "
b10111100101110 $
#9
b111001111101110 !
b111001111101110 &
b101001011101100 #
b101001011101100 %
b11000100101110 "
b11000100101110 $
#10
b11001111111111 !
b11001111111111 &
b10001101100111 #
b10001101100111 %
b11001010111100 "
b11001010111100 $
#11
b1111001111110110 !
b1111001111110110 &
b1110000110100110 #
b1110000110100110 %
b11001101110010 "
b11001101110010 $
#12
b1111111110011111 !
b1111111110011111 &
b1111111010001110 #
b1111111010001110 %
b100101100010001 "
b100101100010001 $
#13
b111001011011011 !
b111001011011011 &
b10001011011011 #
b10001011011011 %
b101001000011011 "
b101001000011011 $
#14
b1101101101010110 !
b1101101101010110 &
b1000100001010010 #
b1000100001010010 %
b101001101010100 "
b101001101010100 $
#15
b101011101111111 !
b101011101111111 &
b100000100110111 #
b100000100110111 %
b101011101101011 "
b101011101101011 $
#16
b1111010110111111 !
b1111010110111111 &
b1000010010100101 #
b1000010010100101 %
b111010100111111 "
b111010100111111 $
#17
b1111111111110110 !
b1111111111110110 &
b1011111101010000 #
b1011111101010000 %
b111101111110110 "
b111101111110110 $
#18
b1111110111101111 !
b1111110111101111 &
b1010110000001110 #
b1010110000001110 %
b111110111101111 "
b111110111101111 $
#19
b1001111111111111 !
b1001111111111111 &
b1111101101011 #
b1111101101011 %
b1000011111011101 "
b1000011111011101 $
#20
b1100111111110011 !
b1100111111110011 &
b100101111100001 #
b100101111100001 %
b1000110000010011 "
b1000110000010011 $
#21
b1011111101011011 !
b1011111101011011 &
b11001000010011 #
b11001000010011 %
b1000110101011001 "
b1000110101011001 $
#22
b1111111101101110 !
b1111111101101110 &
b111110101101110 #
b111110101101110 %
b1001011001001000 "
b1001011001001000 $
#23
b1001101111111111 !
b1001101111111111 &
b1000100111101100 #
b1000100111101100 %
b1001101011110111 "
b1001101011110111 $
#24
b1111101011000110 !
b1111101011000110 &
b111001011000110 #
b111001011000110 %
b1010101000000010 "
b1010101000000010 $
#25
b1111001101111111 !
b1111001101111111 &
b111001001011111 #
b111001001011111 %
b1011001100111001 "
b1011001100111001 $
#26
b1111101011010101 !
b1111101011010101 &
b1110001000010101 #
b1110001000010101 %
b1011101011000001 "
b1011101011000001 $
#27
b1101110111111000 !
b1101110111111000 &
b1000101101000 #
b1000101101000 %
b1100110111011000 "
b1100110111011000 $
#28
b1110111101110111 !
b1110111101110111 &
b1010010100110110 #
b1010010100110110 %
b1100111001100101 "
b1100111001100101 $
#29
b1111000111011101 !
b1111000111011101 &
b1011000111000101 #
b1011000111000101 %
b1111000111011001 "
b1111000111011001 $
