Elementos de Sistemas Computacionais/DLatch.v
/* módulo DLatch */

`ifndef _DLatch_
`define _DLatch_

module DLatch(q, d, clk);
    input d, clk;
    output q;
    wire w1, w2, w3, w4, w5, w6, w7, w8, w9, nq;

    nand nand1(w2, d, clk);
    not not1(w1, d);
    nand nand2(w5, w2, w3);
    nand nand3(w4, clk, w1);
    nand nand4(w3, w5, w4);
    not not2(w7, clk);
    not not3(w6, w5);
    nand nand5(w8, w5, w7);
    nand nand6(q, w8, nq);
    nand nand7(w9, w7, w6);
    nand nand8(nq, q, w9);

    // Descrição de conexões internas do módulo

endmodule

`endif

Elementos de Sistemas Computacionais/Mux.v
/* módulo Mux */

`ifndef _Mux_
`define _Mux_

module Mux(out, a, b, sel);
    input a, b, sel;
    output out;
    wire w0, w1, w2;

    
    nand nand0(w0, a, w2);
    nand nand1(w1, b, sel);
    nand nand2(out, w0, w1);
    not not0(w2, sel);

    // Descrição de conexões internas do módulo

endmodule

`endif

Elementos de Sistemas Computacionais/Bit.v
/* módulo Bit */

`ifndef _Bit_
`define _Bit_

`include "Mux.v"
`include "DLatch.v"

module Bit(out, in, load, clk);
    input in, load, clk;
    output out;
    wire w0, w1;

    Mux mux0(w0, w1, in, load);
    DLatch dff(w1, w0, clk);

    assign out = w1;


    // Descrição de conexões internas do módulo

endmodule

`endif

Elementos de Sistemas Computacionais/Register16.v
/* módulo Register16 */

`ifndef _Register16_
`define _Register16_
`include "Bit.v"

module Register16(out, in, load, clk);
    input load, clk;
    input [15:0] in;
    output [15:0] out;

    Bit bit0(out[0], in[0], load, clk);
    Bit bit1(out[1], in[1], load, clk);
    Bit bit2(out[2], in[2], load, clk);
    Bit bit3(out[3], in[3], load, clk);
    Bit bit4(out[4], in[4], load, clk);
    Bit bit5(out[5], in[5], load, clk);
    Bit bit6(out[6], in[6], load, clk);
    Bit bit7(out[7], in[7], load, clk);
    Bit bit8(out[8], in[8], load, clk);
    Bit bit9(out[9], in[9], load, clk);
    Bit bit10(out[10], in[10], load, clk);
    Bit bit11(out[11], in[11], load, clk);
    Bit bit12(out[12], in[12], load, clk);
    Bit bit13(out[13], in[13], load, clk);
    Bit bit14(out[14], in[14], load, clk);
    Bit bit15(out[15], in[15], load, clk);
    

    // Descrição de conexões internas do módulo

endmodule

`endif

Elementos de Sistemas Computacionais/tb_Register16.v
/* testbench para Register16 */
/* ordem de portas: out, in, load, clk */
/* input [15:0] in; */
/* input load, clk; */
/* output [15:0] out; */

`include "Register16.v"

`define assert(signal, value) \
    if (signal !== value) \
    begin \
        $display("ASSERTION FAILED in %m: signal != value"); \
        $finish; \
    end else begin \
        $display("Success! %m: signal = value"); \
    end

module tb_Register16;
    reg [15:0] in;
    reg load, clk;
    wire [15:0] out;

    Register16 reg0(out, in, load, clk);
    
    always
    begin
        #1 clk = ~clk;
    end
    
    initial
    begin
        $dumpfile("tb_Register16.vcd");
        $dumpvars(0, tb_Register16);

        clk = 0;

        in = 16'b0; load = 1; #3;
        `assert(out, 16'b0)

        in = 16'b0000000000000000; load = 1; #3;
        `assert(out, 16'b0000000000000000);

        in = 16'b0000011001000110; load = 0; #3;
        `assert(out, 16'b0000000000000000);

        in = 16'b0000100001100000; load = 1; #3;
        `assert(out, 16'b0000100001100000);

        in = 16'b0001001001100101; load = 0; #3;
        `assert(out, 16'b0000100001100000);

        in = 16'b0001001110011011; load = 1; #3;
        `assert(out, 16'b0001001110011011);

        in = 16'b0001111001110110; load = 0; #3;
        `assert(out, 16'b0001001110011011);

        in = 16'b0010000001110100; load = 1; #3;
        `assert(out, 16'b0010000001110100);

        in = 16'b0010010101101000; load = 0; #3;
        `assert(out, 16'b0010000001110100);

        in = 16'b0010011100011111; load = 1; #3;
        `assert(out, 16'b0010011100011111);

        in = 16'b0010101010110011; load = 0; #3;
        `assert(out, 16'b0010011100011111);

        in = 16'b0011001010000001; load = 1; #3;
        `assert(out, 16'b0011001010000001);

        in = 16'b0101001001011111; load = 0; #3;
        `assert(out, 16'b0011001010000001);

        in = 16'b0101001011010000; load = 1; #3;
        `assert(out, 16'b0101001011010000);

        in = 16'b0101100011001001; load = 0; #3;
        `assert(out, 16'b0101001011010000);

        in = 16'b0101110110100111; load = 1; #3;
        `assert(out, 16'b0101110110100111);

        in = 16'b1000000110000101; load = 0; #3;
        `assert(out, 16'b0101110110100111);

        in = 16'b1000110101100011; load = 1; #3;
        `assert(out, 16'b1000110101100011);

        in = 16'b1001000001001110; load = 0; #3;
        `assert(out, 16'b1000110101100011);

        in = 16'b1001001100111100; load = 1; #3;
        `assert(out, 16'b1001001100111100);

        in = 16'b1010100101100001; load = 0; #3;
        `assert(out, 16'b1001001100111100);

        in = 16'b1010101101010101; load = 1; #3;
        `assert(out, 16'b1010101101010101);

        in = 16'b1011001010111001; load = 0; #3;
        `assert(out, 16'b1010101101010101);

        in = 16'b1011100010000111; load = 1; #3;
        `assert(out, 16'b1011100010000111);

        in = 16'b1100100001010011; load = 0; #3;
        `assert(out, 16'b1011100010000111);

        in = 16'b1101011110111110; load = 1; #3;
        `assert(out, 16'b1101011110111110);

        in = 16'b1101101011111101; load = 0; #3;
        `assert(out, 16'b1101011110111110);

        in = 16'b1110001101011000; load = 1; #3;
        `assert(out, 16'b1110001101011000);

        in = 16'b1110011101101000; load = 0; #3;
        `assert(out, 16'b1110001101011000);

        in = 16'b1110111010100100; load = 1; #3;
        `assert(out, 16'b1110111010100100);

        in = 16'b1111111111111111; load = 0; #3;
        `assert(out, 16'b1110111010100100);

        $finish;
    end

endmodule

Elementos de Sistemas Computacionais/tb_Register16.vcd
$date
	Wed May 03 22:03:34 2023
$end
$version
	Icarus Verilog
$end
$timescale
	1s
$end
$scope module tb_Register16 $end
$var wire 16 ! out [15:0] $end
$var reg 1 " clk $end
$var reg 16 # in [15:0] $end
$var reg 1 $ load $end
$scope module reg0 $end
$var wire 1 " clk $end
$var wire 16 % in [15:0] $end
$var wire 1 $ load $end
$var wire 16 & out [15:0] $end
$scope module bit0 $end
$var wire 1 " clk $end
$var wire 1 ' in $end
$var wire 1 $ load $end
$var wire 1 ( out $end
$var wire 1 ) w1 $end
$var wire 1 * w0 $end
$scope module dff $end
$var wire 1 " clk $end
$var wire 1 + nq $end
$var wire 1 ) q $end
$var wire 1 , w1 $end
$var wire 1 - w2 $end
$var wire 1 . w3 $end
$var wire 1 / w4 $end
$var wire 1 0 w5 $end
$var wire 1 1 w6 $end
$var wire 1 2 w7 $end
$var wire 1 3 w8 $end
$var wire 1 4 w9 $end
$var wire 1 * d $end
$upscope $end
$scope module mux0 $end
$var wire 1 ) a $end
$var wire 1 ' b $end
$var wire 1 * out $end
$var wire 1 $ sel $end
$var wire 1 5 w0 $end
$var wire 1 6 w1 $end
$var wire 1 7 w2 $end
$upscope $end
$upscope $end
$scope module bit1 $end
$var wire 1 " clk $end
$var wire 1 8 in $end
$var wire 1 $ load $end
$var wire 1 9 out $end
$var wire 1 : w1 $end
$var wire 1 ; w0 $end
$scope module dff $end
$var wire 1 " clk $end
$var wire 1 < nq $end
$var wire 1 : q $end
$var wire 1 = w1 $end
$var wire 1 > w2 $end
$var wire 1 ? w3 $end
$var wire 1 @ w4 $end
$var wire 1 A w5 $end
$var wire 1 B w6 $end
$var wire 1 C w7 $end
$var wire 1 D w8 $end
$var wire 1 E w9 $end
$var wire 1 ; d $end
$upscope $end
$scope module mux0 $end
$var wire 1 : a $end
$var wire 1 8 b $end
$var wire 1 ; out $end
$var wire 1 $ sel $end
$var wire 1 F w0 $end
$var wire 1 G w1 $end
$var wire 1 H w2 $end
$upscope $end
$upscope $end
$scope module bit10 $end
$var wire 1 " clk $end
$var wire 1 I in $end
$var wire 1 $ load $end
$var wire 1 J out $end
$var wire 1 K w1 $end
$var wire 1 L w0 $end
$scope module dff $end
$var wire 1 " clk $end
$var wire 1 M nq $end
$var wire 1 K q $end
$var wire 1 N w1 $end
$var wire 1 O w2 $end
$var wire 1 P w3 $end
$var wire 1 Q w4 $end
$var wire 1 R w5 $end
$var wire 1 S w6 $end
$var wire 1 T w7 $end
$var wire 1 U w8 $end
$var wire 1 V w9 $end
$var wire 1 L d $end
$upscope $end
$scope module mux0 $end
$var wire 1 K a $end
$var wire 1 I b $end
$var wire 1 L out $end
$var wire 1 $ sel $end
$var wire 1 W w0 $end
$var wire 1 X w1 $end
$var wire 1 Y w2 $end
$upscope $end
$upscope $end
$scope module bit11 $end
$var wire 1 " clk $end
$var wire 1 Z in $end
$var wire 1 $ load $end
$var wire 1 [ out $end
$var wire 1 \ w1 $end
$var wire 1 ] w0 $end
$scope module dff $end
$var wire 1 " clk $end
$var wire 1 ^ nq $end
$var wire 1 \ q $end
$var wire 1 _ w1 $end
$var wire 1 ` w2 $end
$var wire 1 a w3 $end
$var wire 1 b w4 $end
$var wire 1 c w5 $end
$var wire 1 d w6 $end
$var wire 1 e w7 $end
$var wire 1 f w8 $end
$var wire 1 g w9 $end
$var wire 1 ] d $end
$upscope $end
$scope module mux0 $end
$var wire 1 \ a $end
$var wire 1 Z b $end
$var wire 1 ] out $end
$var wire 1 $ sel $end
$var wire 1 h w0 $end
$var wire 1 i w1 $end
$var wire 1 j w2 $end
$upscope $end
$upscope $end
$scope module bit12 $end
$var wire 1 " clk $end
$var wire 1 k in $end
$var wire 1 $ load $end
$var wire 1 l out $end
$var wire 1 m w1 $end
$var wire 1 n w0 $end
$scope module dff $end
$var wire 1 " clk $end
$var wire 1 o nq $end
$var wire 1 m q $end
$var wire 1 p w1 $end
$var wire 1 q w2 $end
$var wire 1 r w3 $end
$var wire 1 s w4 $end
$var wire 1 t w5 $end
$var wire 1 u w6 $end
$var wire 1 v w7 $end
$var wire 1 w w8 $end
$var wire 1 x w9 $end
$var wire 1 n d $end
$upscope $end
$scope module mux0 $end
$var wire 1 m a $end
$var wire 1 k b $end
$var wire 1 n out $end
$var wire 1 $ sel $end
$var wire 1 y w0 $end
$var wire 1 z w1 $end
$var wire 1 { w2 $end
$upscope $end
$upscope $end
$scope module bit13 $end
$var wire 1 " clk $end
$var wire 1 | in $end
$var wire 1 $ load $end
$var wire 1 } out $end
$var wire 1 ~ w1 $end
$var wire 1 !" w0 $end
$scope module dff $end
$var wire 1 " clk $end
$var wire 1 "" nq $end
$var wire 1 ~ q $end
$var wire 1 #" w1 $end
$var wire 1 $" w2 $end
$var wire 1 %" w3 $end
$var wire 1 &" w4 $end
$var wire 1 '" w5 $end
$var wire 1 (" w6 $end
$var wire 1 )" w7 $end
$var wire 1 *" w8 $end
$var wire 1 +" w9 $end
$var wire 1 !" d $end
$upscope $end
$scope module mux0 $end
$var wire 1 ~ a $end
$var wire 1 | b $end
$var wire 1 !" out $end
$var wire 1 $ sel $end
$var wire 1 ," w0 $end
$var wire 1 -" w1 $end
$var wire 1 ." w2 $end
$upscope $end
$upscope $end
$scope module bit14 $end
$var wire 1 " clk $end
$var wire 1 /" in $end
$var wire 1 $ load $end
$var wire 1 0" out $end
$var wire 1 1" w1 $end
$var wire 1 2" w0 $end
$scope module dff $end
$var wire 1 " clk $end
$var wire 1 3" nq $end
$var wire 1 1" q $end
$var wire 1 4" w1 $end
$var wire 1 5" w2 $end
$var wire 1 6" w3 $end
$var wire 1 7" w4 $end
$var wire 1 8" w5 $end
$var wire 1 9" w6 $end
$var wire 1 :" w7 $end
$var wire 1 ;" w8 $end
$var wire 1 <" w9 $end
$var wire 1 2" d $end
$upscope $end
$scope module mux0 $end
$var wire 1 1" a $end
$var wire 1 /" b $end
$var wire 1 2" out $end
$var wire 1 $ sel $end
$var wire 1 =" w0 $end
$var wire 1 >" w1 $end
$var wire 1 ?" w2 $end
$upscope $end
$upscope $end
$scope module bit15 $end
$var wire 1 " clk $end
$var wire 1 @" in $end
$var wire 1 $ load $end
$var wire 1 A" out $end
$var wire 1 B" w1 $end
$var wire 1 C" w0 $end
$scope module dff $end
$var wire 1 " clk $end
$var wire 1 D" nq $end
$var wire 1 B" q $end
$var wire 1 E" w1 $end
$var wire 1 F" w2 $end
$var wire 1 G" w3 $end
$var wire 1 H" w4 $end
$var wire 1 I" w5 $end
$var wire 1 J" w6 $end
$var wire 1 K" w7 $end
$var wire 1 L" w8 $end
$var wire 1 M" w9 $end
$var wire 1 C" d $end
$upscope $end
$scope module mux0 $end
$var wire 1 B" a $end
$var wire 1 @" b $end
$var wire 1 C" out $end
$var wire 1 $ sel $end
$var wire 1 N" w0 $end
$var wire 1 O" w1 $end
$var wire 1 P" w2 $end
$upscope $end
$upscope $end
$scope module bit2 $end
$var wire 1 " clk $end
$var wire 1 Q" in $end
$var wire 1 $ load $end
$var wire 1 R" out $end
$var wire 1 S" w1 $end
$var wire 1 T" w0 $end
$scope module dff $end
$var wire 1 " clk $end
$var wire 1 U" nq $end
$var wire 1 S" q $end
$var wire 1 V" w1 $end
$var wire 1 W" w2 $end
$var wire 1 X" w3 $end
$var wire 1 Y" w4 $end
$var wire 1 Z" w5 $end
$var wire 1 [" w6 $end
$var wire 1 \" w7 $end
$var wire 1 ]" w8 $end
$var wire 1 ^" w9 $end
$var wire 1 T" d $end
$upscope $end
$scope module mux0 $end
$var wire 1 S" a $end
$var wire 1 Q" b $end
$var wire 1 T" out $end
$var wire 1 $ sel $end
$var wire 1 _" w0 $end
$var wire 1 `" w1 $end
$var wire 1 a" w2 $end
$upscope $end
$upscope $end
$scope module bit3 $end
$var wire 1 " clk $end
$var wire 1 b" in $end
$var wire 1 $ load $end
$var wire 1 c" out $end
$var wire 1 d" w1 $end
$var wire 1 e" w0 $end
$scope module dff $end
$var wire 1 " clk $end
$var wire 1 f" nq $end
$var wire 1 d" q $end
$var wire 1 g" w1 $end
$var wire 1 h" w2 $end
$var wire 1 i" w3 $end
$var wire 1 j" w4 $end
$var wire 1 k" w5 $end
$var wire 1 l" w6 $end
$var wire 1 m" w7 $end
$var wire 1 n" w8 $end
$var wire 1 o" w9 $end
$var wire 1 e" d $end
$upscope $end
$scope module mux0 $end
$var wire 1 d" a $end
$var wire 1 b" b $end
$var wire 1 e" out $end
$var wire 1 $ sel $end
$var wire 1 p" w0 $end
$var wire 1 q" w1 $end
$var wire 1 r" w2 $end
$upscope $end
$upscope $end
$scope module bit4 $end
$var wire 1 " clk $end
$var wire 1 s" in $end
$var wire 1 $ load $end
$var wire 1 t" out $end
$var wire 1 u" w1 $end
$var wire 1 v" w0 $end
$scope module dff $end
$var wire 1 " clk $end
$var wire 1 w" nq $end
$var wire 1 u" q $end
$var wire 1 x" w1 $end
$var wire 1 y" w2 $end
$var wire 1 z" w3 $end
$var wire 1 {" w4 $end
$var wire 1 |" w5 $end
$var wire 1 }" w6 $end
$var wire 1 ~" w7 $end
$var wire 1 !# w8 $end
$var wire 1 "# w9 $end
$var wire 1 v" d $end
$upscope $end
$scope module mux0 $end
$var wire 1 u" a $end
$var wire 1 s" b $end
$var wire 1 v" out $end
$var wire 1 $ sel $end
$var wire 1 ## w0 $end
$var wire 1 $# w1 $end
$var wire 1 %# w2 $end
$upscope $end
$upscope $end
$scope module bit5 $end
$var wire 1 " clk $end
$var wire 1 &# in $end
$var wire 1 $ load $end
$var wire 1 '# out $end
$var wire 1 (# w1 $end
$var wire 1 )# w0 $end
$scope module dff $end
$var wire 1 " clk $end
$var wire 1 *# nq $end
$var wire 1 (# q $end
$var wire 1 +# w1 $end
$var wire 1 ,# w2 $end
$var wire 1 -# w3 $end
$var wire 1 .# w4 $end
$var wire 1 /# w5 $end
$var wire 1 0# w6 $end
$var wire 1 1# w7 $end
$var wire 1 2# w8 $end
$var wire 1 3# w9 $end
$var wire 1 )# d $end
$upscope $end
$scope module mux0 $end
$var wire 1 (# a $end
$var wire 1 &# b $end
$var wire 1 )# out $end
$var wire 1 $ sel $end
$var wire 1 4# w0 $end
$var wire 1 5# w1 $end
$var wire 1 6# w2 $end
$upscope $end
$upscope $end
$scope module bit6 $end
$var wire 1 " clk $end
$var wire 1 7# in $end
$var wire 1 $ load $end
$var wire 1 8# out $end
$var wire 1 9# w1 $end
$var wire 1 :# w0 $end
$scope module dff $end
$var wire 1 " clk $end
$var wire 1 ;# nq $end
$var wire 1 9# q $end
$var wire 1 <# w1 $end
$var wire 1 =# w2 $end
$var wire 1 ># w3 $end
$var wire 1 ?# w4 $end
$var wire 1 @# w5 $end
$var wire 1 A# w6 $end
$var wire 1 B# w7 $end
$var wire 1 C# w8 $end
$var wire 1 D# w9 $end
$var wire 1 :# d $end
$upscope $end
$scope module mux0 $end
$var wire 1 9# a $end
$var wire 1 7# b $end
$var wire 1 :# out $end
$var wire 1 $ sel $end
$var wire 1 E# w0 $end
$var wire 1 F# w1 $end
$var wire 1 G# w2 $end
$upscope $end
$upscope $end
$scope module bit7 $end
$var wire 1 " clk $end
$var wire 1 H# in $end
$var wire 1 $ load $end
$var wire 1 I# out $end
$var wire 1 J# w1 $end
$var wire 1 K# w0 $end
$scope module dff $end
$var wire 1 " clk $end
$var wire 1 L# nq $end
$var wire 1 J# q $end
$var wire 1 M# w1 $end
$var wire 1 N# w2 $end
$var wire 1 O# w3 $end
$var wire 1 P# w4 $end
$var wire 1 Q# w5 $end
$var wire 1 R# w6 $end
$var wire 1 S# w7 $end
$var wire 1 T# w8 $end
$var wire 1 U# w9 $end
$var wire 1 K# d $end
$upscope $end
$scope module mux0 $end
$var wire 1 J# a $end
$var wire 1 H# b $end
$var wire 1 K# out $end
$var wire 1 $ sel $end
$var wire 1 V# w0 $end
$var wire 1 W# w1 $end
$var wire 1 X# w2 $end
$upscope $end
$upscope $end
$scope module bit8 $end
$var wire 1 " clk $end
$var wire 1 Y# in $end
$var wire 1 $ load $end
$var wire 1 Z# out $end
$var wire 1 [# w1 $end
$var wire 1 \# w0 $end
$scope module dff $end
$var wire 1 " clk $end
$var wire 1 ]# nq $end
$var wire 1 [# q $end
$var wire 1 ^# w1 $end
$var wire 1 _# w2 $end
$var wire 1 `# w3 $end
$var wire 1 a# w4 $end
$var wire 1 b# w5 $end
$var wire 1 c# w6 $end
$var wire 1 d# w7 $end
$var wire 1 e# w8 $end
$var wire 1 f# w9 $end
$var wire 1 \# d $end
$upscope $end
$scope module mux0 $end
$var wire 1 [# a $end
$var wire 1 Y# b $end
$var wire 1 \# out $end
$var wire 1 $ sel $end
$var wire 1 g# w0 $end
$var wire 1 h# w1 $end
$var wire 1 i# w2 $end
$upscope $end
$upscope $end
$scope module bit9 $end
$var wire 1 " clk $end
$var wire 1 j# in $end
$var wire 1 $ load $end
$var wire 1 k# out $end
$var wire 1 l# w1 $end
$var wire 1 m# w0 $end
$scope module dff $end
$var wire 1 " clk $end
$var wire 1 n# nq $end
$var wire 1 l# q $end
$var wire 1 o# w1 $end
$var wire 1 p# w2 $end
$var wire 1 q# w3 $end
$var wire 1 r# w4 $end
$var wire 1 s# w5 $end
$var wire 1 t# w6 $end
$var wire 1 u# w7 $end
$var wire 1 v# w8 $end
$var wire 1 w# w9 $end
$var wire 1 m# d $end
$upscope $end
$scope module mux0 $end
$var wire 1 l# a $end
$var wire 1 j# b $end
$var wire 1 m# out $end
$var wire 1 $ sel $end
$var wire 1 x# w0 $end
$var wire 1 y# w1 $end
$var wire 1 z# w2 $end
$upscope $end
$upscope $end
$upscope $end
$upscope $end
$enddefinitions $end
$comment Show the parameter values. $end
$dumpall
$end
#0
$dumpvars
0z#
1y#
1x#
xw#
xv#
1u#
xt#
xs#
1r#
xq#
1p#
1o#
xn#
0m#
xl#
xk#
0j#
0i#
1h#
1g#
xf#
xe#
1d#
xc#
xb#
1a#
x`#
1_#
1^#
x]#
0\#
x[#
xZ#
0Y#
0X#
1W#
1V#
xU#
xT#
1S#
xR#
xQ#
1P#
xO#
1N#
1M#
xL#
0K#
xJ#
xI#
0H#
0G#
1F#
1E#
xD#
xC#
1B#
xA#
x@#
1?#
x>#
1=#
1<#
x;#
0:#
x9#
x8#
07#
06#
15#
14#
x3#
x2#
11#
x0#
x/#
1.#
x-#
1,#
1+#
x*#
0)#
x(#
x'#
0&#
0%#
1$#
1##
x"#
x!#
1~"
x}"
x|"
1{"
xz"
1y"
1x"
xw"
0v"
xu"
xt"
0s"
0r"
1q"
1p"
xo"
xn"
1m"
xl"
xk"
1j"
xi"
1h"
1g"
xf"
0e"
xd"
xc"
0b"
0a"
1`"
1_"
x^"
x]"
1\"
x["
xZ"
1Y"
xX"
1W"
1V"
xU"
0T"
xS"
xR"
0Q"
0P"
1O"
1N"
xM"
xL"
1K"
xJ"
xI"
1H"
xG"
1F"
1E"
xD"
0C"
xB"
xA"
0@"
0?"
1>"
1="
x<"
x;"
1:"
x9"
x8"
17"
x6"
15"
14"
x3"
02"
x1"
x0"
0/"
0."
1-"
1,"
x+"
x*"
1)"
x("
x'"
1&"
x%"
1$"
1#"
x""
0!"
x~
x}
0|
0{
1z
1y
xx
xw
1v
xu
xt
1s
xr
1q
1p
xo
0n
xm
xl
0k
0j
1i
1h
xg
xf
1e
xd
xc
1b
xa
1`
1_
x^
0]
x\
x[
0Z
0Y
1X
1W
xV
xU
1T
xS
xR
1Q
xP
1O
1N
xM
0L
xK
xJ
0I
0H
1G
1F
xE
xD
1C
xB
xA
1@
x?
1>
1=
x<
0;
x:
x9
08
07
16
15
x4
x3
12
x1
x0
1/
x.
1-
1,
x+
0*
x)
x(
0'
bx &
b0 %
1$
b0 #
0"
bx !
$end
#1
11
1B
1S
1d
1u
1("
19"
1J"
1["
1l"
1}"
10#
1A#
1R#
1c#
1t#
00
0A
0R
0c
0t
0'"
08"
0I"
0Z"
0k"
0|"
0/#
0@#
0Q#
0b#
0s#
1.
13
14
1?
1D
1E
1P
1U
1V
1a
1f
1g
1r
1w
1x
1%"
1*"
1+"
16"
1;"
1<"
1G"
1L"
1M"
1X"
1]"
1^"
1i"
1n"
1o"
1z"
1!#
1"#
1-#
12#
13#
1>#
1C#
1D#
1O#
1T#
1U#
1`#
1e#
1f#
1q#
1v#
1w#
0/
02
0@
0C
0Q
0T
0b
0e
0s
0v
0&"
0)"
07"
0:"
0H"
0K"
0Y"
0\"
0j"
0m"
0{"
0~"
0.#
01#
0?#
0B#
0P#
0S#
0a#
0d#
0r#
0u#
1"
#2
0(
0)
09
0:
0J
0K
0[
0\
0l
0m
0}
0~
00"
01"
0A"
0B"
0R"
0S"
0c"
0d"
0t"
0u"
0'#
0(#
08#
09#
0I#
0J#
0Z#
0[#
b0 !
b0 &
0k#
0l#
1+
1<
1M
1^
1o
1""
13"
1D"
1U"
1f"
1w"
1*#
1;#
1L#
1]#
1n#
04
0E
0V
0g
0x
0+"
0<"
0M"
0^"
0o"
0"#
03#
0D#
0U#
0f#
0w#
1/
12
1@
1C
1Q
1T
1b
1e
1s
1v
1&"
1)"
17"
1:"
1H"
1K"
1Y"
1\"
1j"
1m"
1{"
1~"
1.#
11#
1?#
1B#
1P#
1S#
1a#
1d#
1r#
1u#
0"
#3
14
1E
1V
1g
1x
1+"
1<"
1M"
1^"
1o"
1"#
13#
1D#
1U#
1f#
1w#
0/
02
0@
0C
0Q
0T
0b
0e
0s
0v
0&"
0)"
07"
0:"
0H"
0K"
0Y"
0\"
0j"
0m"
0{"
0~"
0.#
01#
0?#
0B#
0P#
0S#
0a#
0d#
0r#
0u#
1"
#4
04
0E
0V
0g
0x
0+"
0<"
0M"
0^"
0o"
0"#
03#
0D#
0U#
0f#
0w#
1/
12
1@
1C
1Q
1T
1b
1e
1s
1v
1&"
1)"
17"
1:"
1H"
1K"
1Y"
1\"
1j"
1m"
1{"
1~"
1.#
11#
1?#
1B#
1P#
1S#
1a#
1d#
1r#
1u#
0"
#5
14
1E
1V
1g
1x
1+"
1<"
1M"
1^"
1o"
1"#
13#
1D#
1U#
1f#
1w#
0/
02
0@
0C
0Q
0T
0b
0e
0s
0v
0&"
0)"
07"
0:"
0H"
0K"
0Y"
0\"
0j"
0m"
0{"
0~"
0.#
01#
0?#
0B#
0P#
0S#
0a#
0d#
0r#
0u#
1"
#6
04
0E
0V
0g
0x
0+"
0<"
0M"
0^"
0o"
0"#
03#
0D#
0U#
0f#
0w#
1/
12
1@
1C
1Q
1T
1b
1e
1s
1v
1&"
1)"
17"
1:"
1H"
1K"
1Y"
1\"
1j"
1m"
1{"
1~"
1.#
11#
1?#
1B#
1P#
1S#
1a#
1d#
1r#
1u#
17
1H
1Y
1j
1{
1."
1?"
1P"
1a"
1r"
1%#
16#
1G#
1X#
1i#
1z#
18
1Q"
17#
1j#
1I
0"
0$
b11001000110 #
b11001000110 %
#7
14
1E
1V
1g
1x
1+"
1<"
1M"
1^"
1o"
1"#
13#
1D#
1U#
1f#
1w#
0/
02
0@
0C
0Q
0T
0b
0e
0s
0v
0&"
0)"
07"
0:"
0H"
0K"
0Y"
0\"
0j"
0m"
0{"
0~"
0.#
01#
0?#
0B#
0P#
0S#
0a#
0d#
0r#
0u#
1"
#8
04
0E
0V
0g
0x
0+"
0<"
0M"
0^"
0o"
0"#
03#
0D#
0U#
0f#
0w#
1/
12
1@
1C
1Q
1T
1b
1e
1s
1v
1&"
1)"
17"
1:"
1H"
1K"
1Y"
1\"
1j"
1m"
1{"
1~"
1.#
11#
1?#
1B#
1P#
1S#
1a#
1d#
1r#
1u#
0"
#9
0a
0d
0-#
00#
0>#
0A#
1c
1/#
1@#
0_
0`
0+#
0,#
0<#
0=#
14
1E
1V
1g
1x
1+"
1<"
1M"
1^"
1o"
1"#
13#
1D#
1U#
1f#
1w#
1]
1)#
1:#
0/
02
0@
0C
0Q
0T
1b
0e
0s
0v
0&"
0)"
07"
0:"
0H"
0K"
0Y"
0\"
0j"
0m"
0{"
0~"
1.#
01#
1?#
0B#
0P#
0S#
0a#
0d#
0r#
0u#
07
0H
0Y
0i
0j
0{
0."
0?"
0P"
0a"
0r"
0%#
05#
06#
0F#
0G#
0X#
0i#
0z#
08
0Q"
1&#
0j#
0I
1Z
1"
1$
b100001100000 #
b100001100000 %
#10
0^
0*#
0;#
1[
1\
1'#
1(#
b100001100000 !
b100001100000 &
18#
19#
04
0E
0V
0f
0x
0+"
0<"
0M"
0^"
0o"
0"#
02#
0C#
0U#
0f#
0w#
1/
12
1@
1C
1Q
1T
1`
1e
1s
1v
1&"
1)"
17"
1:"
1H"
1K"
1Y"
1\"
1j"
1m"
1{"
1~"
1,#
11#
1=#
1B#
1P#
1S#
1a#
1d#
1r#
1u#
0"
#11
14
1E
1V
1f
1x
1+"
1<"
1M"
1^"
1o"
1"#
12#
1C#
1U#
1f#
1w#
0/
02
0@
0C
0Q
0T
0`
0e
0s
0v
0&"
0)"
07"
0:"
0H"
0K"
0Y"
0\"
0j"
0m"
0{"
0~"
0,#
01#
0=#
0B#
0P#
0S#
0a#
0d#
0r#
0u#
1"
#12
04
0E
0V
0f
0x
0+"
0<"
0M"
0^"
0o"
0"#
02#
0C#
0U#
0f#
0w#
0h
04#
0E#
1/
12
1@
1C
1Q
1T
1`
1e
1s
1v
1&"
1)"
17"
1:"
1H"
1K"
1Y"
1\"
1j"
1m"
1{"
1~"
1,#
11#
1=#
1B#
1P#
1S#
1a#
1d#
1r#
1u#
17
1H
1Y
1i
1j
1{
1."
1?"
1P"
1a"
1r"
1%#
15#
16#
1F#
1G#
1X#
1i#
1z#
1'
1Q"
1j#
0Z
1k
0"
0$
b1001001100101 #
b1001001100101 %
#13
14
1E
1V
1f
1x
1+"
1<"
1M"
1^"
1o"
1"#
12#
1C#
1U#
1f#
1w#
0/
02
0@
0C
0Q
0T
0`
0e
0s
0v
0&"
0)"
07"
0:"
0H"
0K"
0Y"
0\"
0j"
0m"
0{"
0~"
0,#
01#
0=#
0B#
0P#
0S#
0a#
0d#
0r#
0u#
1"
#14
04
0E
0V
0f
0x
0+"
0<"
0M"
0^"
0o"
0"#
02#
0C#
0U#
0f#
0w#
1/
12
1@
1C
1Q
1T
1`
1e
1s
1v
1&"
1)"
17"
1:"
1H"
1K"
1Y"
1\"
1j"
1m"
1{"
1~"
1,#
11#
1=#
1B#
1P#
1S#
1a#
1d#
1r#
1u#
0"
#15
1d
10#
1A#
0c
0/#
0@#
1a
1-#
1>#
0.
01
0?
0B
0b
0r
0u
0i"
0l"
0z"
0}"
0.#
0?#
0O#
0R#
0`#
0c#
0q#
0t#
10
1A
1_
1t
1k"
1|"
1+#
1<#
1Q#
1b#
1s#
0,
0-
0=
0>
0]
0p
0q
0g"
0h"
0x"
0y"
0)#
0:#
0M#
0N#
0^#
0_#
0o#
0p#
14
1E
1V
1f
1x
1+"
1<"
1M"
1^"
1o"
1"#
12#
1C#
1U#
1f#
1w#
1*
1;
1h
1n
1e"
1v"
14#
1E#
1K#
1\#
1m#
1/
02
1@
0C
0Q
0T
1`
0e
1s
0v
0&"
0)"
07"
0:"
0H"
0K"
0Y"
0\"
1j"
0m"
1{"
0~"
1,#
01#
1=#
0B#
1P#
0S#
1a#
0d#
1r#
0u#
06
07
0G
0H
0Y
0j
0z
0{
0."
0?"
0P"
0a"
0q"
0r"
0$#
0%#
06#
0G#
0W#
0X#
0h#
0i#
0y#
0z#
18
0Q"
1b"
1s"
0&#
07#
1H#
1Y#
1"
1$
b1001110011011 #
b1001110011011 %
#16
0+
0<
0[
0\
0o
0f"
0w"
0'#
0(#
08#
09#
0L#
0]#
0n#
1(
1)
19
1:
1^
1l
1m
1c"
1d"
1t"
1u"
1*#
1;#
1I#
1J#
1Z#
1[#
b1001110011011 !
b1001110011011 &
1k#
1l#
03
0D
0V
0g
0w
0+"
0<"
0M"
0^"
0n"
0!#
03#
0D#
0T#
0e#
0v#
1-
12
1>
1C
1Q
1T
1b
1e
1q
1v
1&"
1)"
17"
1:"
1H"
1K"
1Y"
1\"
1h"
1m"
1y"
1~"
1.#
11#
1?#
1B#
1N#
1S#
1_#
1d#
1p#
1u#
0"
